Workbook

Sheet Case Guide
A1: Case 7b: missing IFRS 17 cohort
A3: Business problem | B3: Synthetic IFRS 17 fulfilment-cash-flow aggregation and accounting bridge.
A4: Decision | B4: A human reviewer decides whether the workbook evidence supports continuing the reporting workflow.
A5: Gate 2 output | B5: Accounting Bridge!B4 (signed closing liability).
A6: Planted issue | B6: The claims aggregation stops before the final populated cohort, excluding EUR 6.2 million.
A7: Expected internal result | B7: Complete and pass because Python reconstructs the workbook formula as written.
A8: Expected external result | B8: Block below the EUR 6.2 million difference using human-entered thresholds.
A10: Manual check | B10: Expected value | C10: Location
A11: Present value of claims | B11: 98000000 | C11: Reserve Summary!B5
A12: Fulfilment cash flows | B12: 92200000 | C12: Reserve Summary!B8
A13: Closing liability | B13: 122200000 | C13: Reserve Summary!B11
A14: Accounting output | B14: -122200000 | C14: Accounting Bridge!B4
A15: Scope boundary | B15: Spreadsheet translation and reconciliation only | C15: No actuarial-methodology validation

Sheet Context
A1: Confirmed workbook context
A3: Field | B3: Workbook value
A4: Entity | B4: Glass Box Life Belgium SA
A5: Period | B5: 31 December 2025
A6: Currency | B6: EUR
A7: Basis | B7: Synthetic IFRS 17 reporting demonstration
A8: Data status | B8: Entirely synthetic

Sheet Assumptions
A1: Synthetic calculation assumptions
A3: Assumption | B3: Value | E3: Status | F3: Claim factor
A4: Risk adjustment | B4: 7800000 | E4: Active | F4: 1
A5: Contractual service margin | B5: 22200000
A6: Currency rounding digits | B6: 0
A7: Active cohort status | B7: Active
A8: Included flag | B8: 1

Sheet Cohort Data
A1: Synthetic IFRS 17 cohort data
A2: All amounts are fictional and stated in EUR.
A3: Cohort ID | B3: Status | C3: Claims PV | D3: Expenses PV | E3: Premiums PV | F3: Included
A4: C-2020 | B4: Active | C4: 18000000 | D4: 2000000 | E4: -3000000 | F4: 1
A5: C-2021 | B5: Active | C5: 20000000 | D5: 2100000 | E5: -3000000 | F5: 1
A6: C-2022 | B6: Active | C6: 17000000 | D6: 2100000 | E6: -3000000 | F6: 1
A7: C-2023 | B7: Active | C7: 21000000 | D7: 2100000 | E7: -3000000 | F7: 1
A8: C-2024 | B8: Active | C8: 22000000 | D8: 2100000 | E8: -3000000 | F8: 1
A9: C-2025 | B9: Active | C9: 6200000 | D9: 2200000 | E9: -3400000 | F9: 1

Sheet Cash Flow Calculation
A1: Cohort cash-flow calculation
A2: The final populated cohort contributes EUR 6.2 million to claims present value.
A3: Cohort ID | B3: Claims PV | C3: Expenses PV | D3: Premiums PV | E3: Fulfilment cash flow
A4: C-2020 | B4: =IF('Cohort Data'!$F4=Assumptions!$B$8,ROUND('Cohort Data'!$C4*VLOOKUP('Cohort Data'!$B4,Assumptions!$E$4:$F$4,2,FALSE()),Assumptions!$B$6),0) -> 18000000 | C4: =ROUND('Cohort Data'!$D4,Assumptions!$B$6) -> 2000000 | D4: =ROUND('Cohort Data'!$E4,Assumptions!$B$6) -> -3000000 | E4: =SUM(B4:D4) -> 17000000
A5: C-2021 | B5: =IF('Cohort Data'!$F5=Assumptions!$B$8,ROUND('Cohort Data'!$C5*VLOOKUP('Cohort Data'!$B5,Assumptions!$E$4:$F$4,2,FALSE()),Assumptions!$B$6),0) -> 20000000 | C5: =ROUND('Cohort Data'!$D5,Assumptions!$B$6) -> 2100000 | D5: =ROUND('Cohort Data'!$E5,Assumptions!$B$6) -> -3000000 | E5: =SUM(B5:D5) -> 19100000
A6: C-2022 | B6: =IF('Cohort Data'!$F6=Assumptions!$B$8,ROUND('Cohort Data'!$C6*VLOOKUP('Cohort Data'!$B6,Assumptions!$E$4:$F$4,2,FALSE()),Assumptions!$B$6),0) -> 17000000 | C6: =ROUND('Cohort Data'!$D6,Assumptions!$B$6) -> 2100000 | D6: =ROUND('Cohort Data'!$E6,Assumptions!$B$6) -> -3000000 | E6: =SUM(B6:D6) -> 16100000
A7: C-2023 | B7: =IF('Cohort Data'!$F7=Assumptions!$B$8,ROUND('Cohort Data'!$C7*VLOOKUP('Cohort Data'!$B7,Assumptions!$E$4:$F$4,2,FALSE()),Assumptions!$B$6),0) -> 21000000 | C7: =ROUND('Cohort Data'!$D7,Assumptions!$B$6) -> 2100000 | D7: =ROUND('Cohort Data'!$E7,Assumptions!$B$6) -> -3000000 | E7: =SUM(B7:D7) -> 20100000
A8: C-2024 | B8: =IF('Cohort Data'!$F8=Assumptions!$B$8,ROUND('Cohort Data'!$C8*VLOOKUP('Cohort Data'!$B8,Assumptions!$E$4:$F$4,2,FALSE()),Assumptions!$B$6),0) -> 22000000 | C8: =ROUND('Cohort Data'!$D8,Assumptions!$B$6) -> 2100000 | D8: =ROUND('Cohort Data'!$E8,Assumptions!$B$6) -> -3000000 | E8: =SUM(B8:D8) -> 21100000
A9: C-2025 | B9: =IF('Cohort Data'!$F9=Assumptions!$B$8,ROUND('Cohort Data'!$C9*VLOOKUP('Cohort Data'!$B9,Assumptions!$E$4:$F$4,2,FALSE()),Assumptions!$B$6),0) -> 6200000 | C9: =ROUND('Cohort Data'!$D9,Assumptions!$B$6) -> 2200000 | D9: =ROUND('Cohort Data'!$E9,Assumptions!$B$6) -> -3400000 | E9: =SUM(B9:D9) -> 5000000

Sheet Reserve Summary
A1: IFRS 17 reserve summary
A2: Workbook calculation as written: final cohort omitted from claims aggregation.
A4: Component | B4: Amount (EUR)
A5: Present value of claims | B5: =SUM('Cash Flow Calculation'!$B$4:$B$8) -> 98000000
A6: Present value of expenses | B6: =SUMIFS('Cash Flow Calculation'!$C$4:$C$9,'Cohort Data'!$F$4:$F$9,Assumptions!$B$8) -> 12600000
A7: Present value of premiums | B7: =SUM('Cash Flow Calculation'!$D$4:$D$9) -> -18400000
A8: Fulfilment cash flows | B8: =SUM(B5:B7) -> 92200000
A9: Risk adjustment | B9: =Assumptions!$B$4 -> 7800000
A10: Contractual service margin | B10: =Assumptions!$B$5 -> 22200000
A11: Closing liability | B11: =SUM(B8:B10) -> 122200000

Sheet Accounting Bridge
A1: Accounting bridge
A2: Credit balances are negative for reconciliation. All figures are synthetic.
A3: Authoritative output | B3: Signed balance (EUR) | C3: Use
A4: Closing liability | B4: =-'Reserve Summary'!B11 -> -122200000 | C4: Designate this monetary output at Gate 2
A5: Closing liability magnitude | B5: ='Reserve Summary'!B11 -> 122200000 | C5: Display only
