Workbook

Sheet Case Guide
A1: Case 9: life pricing with an incomplete reconstruction
A3: Business problem | B3: Synthetic protection-product pricing projection used for a launch discussion.
A4: Workbook result | B4: The workbook displays a EUR 4.6 million present-value margin.
A5: Independent context | B5: A separately controlled pricing result is negative EUR 4.8 million, an illustrative EUR 9.4 million swing.
A6: Gate 2 output | B6: Profitability Summary!B8 (designated profitability result).
A7: Published boundary | B7: IRR is outside the current reconstruction catalogue and is retained verbatim; SUMPRODUCT reconstructs independently.
A8: Expected internal result | B8: INCOMPLETE. The cached workbook result is visible but is not reconstructed or verified.
A9: Expected external result | B9: NOT PERFORMED. No accounting-reference figures are supplied.
A10: Gate 3 demonstration | B10: Without the explicit existing incomplete-result acknowledgement, Gate 3 blocks and Gate 4/PDF remain unavailable.
A11: Methodology boundary | B11: The independent negative result is contextual evidence, not a result certified by Glass Box.
A13: Manual check | B13: Expected value | C13: Location
A14: Annual premium volume | B14: 120000000 | C14: Product Assumptions!B4
A15: Approved lapse | B15: 0.06 | C15: Product Assumptions!B5
A16: Embedded lapse | B16: 0.03 | C16: Policy Projection!C4
A17: Workbook PV margin | B17: 4600000 | C17: Profitability Summary!B5
A18: Independent pricing result | B18: -4800000 | C18: Independent Pricing Reference!B4
A19: Illustrative economic swing | B19: 9400000 | C19: Independent Pricing Reference!B5

Sheet Context
A1: Confirmed workbook context
A3: Field | B3: Workbook value
A4: Entity | B4: Glass Box Life Belgium SA
A5: Period | B5: 31 December 2025
A6: Currency | B6: EUR
A7: Basis | B7: Synthetic life-pricing demonstration
A8: Data status | B8: Entirely synthetic

Sheet Product Assumptions
A1: Approved product assumptions
A3: Assumption | B3: Approved value | E3: Product code | F3: Claims factor
A4: Expected annual premium volume | B4: 120000000 | E4: PROTECT | F4: 0.72
A5: Approved annual lapse | B5: 0.06
A6: Discount rate | B6: 0.05
A7: Claims ratio | B7: 0.72
A8: Expense ratio | B8: 0.1
A9: Commission ratio | B9: 0.1
A10: Acquisition cash outflow | B10: 34659130

Sheet Policy Projection
A1: Policy projection
A2: The approved 6% lapse is shown separately; the projection embeds 3% in C4.
A3: Year | B3: Premium volume | C3: Lapse used | D3: In-force flag | E3: Product code
A4: 1 | B4: ='Product Assumptions'!$B$4 -> 120000000 | C4: =IF(B4>0,0.03,0) -> 0.03 | D4: =IF(B4>0,1,0) -> 1 | E4: PROTECT
A5: 2 | B5: =ROUND(B4-B4*C4,0) -> 116400000 | C5: =C4 -> 0.03 | D5: =IF(B5>0,1,0) -> 1 | E5: PROTECT
A6: 3 | B6: =ROUND(B5-B5*C5,0) -> 112908000 | C6: =C4 -> 0.03 | D6: =IF(B6>0,1,0) -> 1 | E6: PROTECT
A7: 4 | B7: =ROUND(B6-B6*C6,0) -> 109520760 | C7: =C4 -> 0.03 | D7: =IF(B7>0,1,0) -> 1 | E7: PROTECT
A8: 5 | B8: =ROUND(B7-B7*C7,0) -> 106235137 | C8: =C4 -> 0.03 | D8: =IF(B8>0,1,0) -> 1 | E8: PROTECT

Sheet Cash Flows
A1: Projection cash flows
A2: Year zero contains acquisition cash outflow; all later rows are supported intermediate calculations.
A3: Year | B3: Premium | C3: Claims | D3: Expenses | E3: Commission | F3: Net cash flow | G3: Discount factor | H3: Status
A4: 0 | B4: 0 | C4: 0 | D4: 0 | E4: 0 | F4: =-'Product Assumptions'!$B$10 -> -34659130 | G4: 1 | H4: Included
A5: 1 | B5: ='Policy Projection'!B4 -> 120000000 | C5: =-ROUND(B5*VLOOKUP('Policy Projection'!E4,'Product Assumptions'!$E$4:$F$4,2,FALSE()),0) -> -86400000 | D5: =-ROUND(B5*'Product Assumptions'!$B$8,0) -> -12000000 | E5: =-ROUND(B5*'Product Assumptions'!$B$9,0) -> -12000000 | F5: =SUM(B5:E5) -> 9600000 | G5: =G4/(1+'Product Assumptions'!$B$6) -> 0.95238095 | H5: Included
A6: 2 | B6: ='Policy Projection'!B5 -> 116400000 | C6: =-ROUND(B6*VLOOKUP('Policy Projection'!E5,'Product Assumptions'!$E$4:$F$4,2,FALSE()),0) -> -83808000 | D6: =-ROUND(B6*'Product Assumptions'!$B$8,0) -> -11640000 | E6: =-ROUND(B6*'Product Assumptions'!$B$9,0) -> -11640000 | F6: =SUM(B6:E6) -> 9312000 | G6: =G5/(1+'Product Assumptions'!$B$6) -> 0.90702948 | H6: Included
A7: 3 | B7: ='Policy Projection'!B6 -> 112908000 | C7: =-ROUND(B7*VLOOKUP('Policy Projection'!E6,'Product Assumptions'!$E$4:$F$4,2,FALSE()),0) -> -81293760 | D7: =-ROUND(B7*'Product Assumptions'!$B$8,0) -> -11290800 | E7: =-ROUND(B7*'Product Assumptions'!$B$9,0) -> -11290800 | F7: =SUM(B7:E7) -> 9032640 | G7: =G6/(1+'Product Assumptions'!$B$6) -> 0.8638376 | H7: Included
A8: 4 | B8: ='Policy Projection'!B7 -> 109520760 | C8: =-ROUND(B8*VLOOKUP('Policy Projection'!E7,'Product Assumptions'!$E$4:$F$4,2,FALSE()),0) -> -78854947 | D8: =-ROUND(B8*'Product Assumptions'!$B$8,0) -> -10952076 | E8: =-ROUND(B8*'Product Assumptions'!$B$9,0) -> -10952076 | F8: =SUM(B8:E8) -> 8761661 | G8: =G7/(1+'Product Assumptions'!$B$6) -> 0.82270247 | H8: Included
A9: 5 | B9: ='Policy Projection'!B8 -> 106235137 | C9: =-ROUND(B9*VLOOKUP('Policy Projection'!E8,'Product Assumptions'!$E$4:$F$4,2,FALSE()),0) -> -76489299 | D9: =-ROUND(B9*'Product Assumptions'!$B$8,0) -> -10623514 | E9: =-ROUND(B9*'Product Assumptions'!$B$9,0) -> -10623514 | F9: =SUM(B9:E9) -> 8498810 | G9: =G8/(1+'Product Assumptions'!$B$6) -> 0.78352617 | H9: Included

Sheet Profitability Summary
A1: Life-product profitability summary
A2: Cached workbook values are not substitutes for unsupported reconstruction.
A4: Metric | B4: Workbook value
A5: Present-value margin | B5: =SUMPRODUCT('Cash Flows'!$F$4:$F$9,'Cash Flows'!$G$4:$G$9) -> 4600000
A6: Internal rate of return | B6: =IRR(NetCashFlows) -> 0.097825791
A7: Profitability ratio | B7: =ROUND(B5/'Product Assumptions'!B4,3) -> 0.038
A8: Designated profitability result | B8: =IF(B6>0,B5,0) -> 4600000
A9: Included projected premium | B9: =SUMIFS('Cash Flows'!B5:B9,'Cash Flows'!H5:H9,"Included") -> 565063897
A10: Included projection periods | B10: =COUNTIFS('Cash Flows'!H5:H9,"Included") -> 5

Sheet Independent Pricing Reference
A1: Independent pricing reference
A2: Contextual evidence only; not a result certified by Glass Box.
A3: Measure | B3: Controlled value
A4: Independent pricing result | B4: -4800000
A5: Illustrative economic swing | B5: ='Profitability Summary'!B5-B4 -> 9400000
