Workbook

Sheet Impact Summary
A1: Case 6: synthetic reserve stress and solvency impact | B1: Case 6: synthetic reserve stress and solvency impact | C1: Case 6: synthetic reserve stress and solvency impact | D1: Case 6: synthetic reserve stress and solvency impact
A2: A baseline-versus-adverse calculation across 300 fictional cohorts. This is a workflow demonstration, not certified actuarial methodology. | B2: A baseline-versus-adverse calculation across 300 fictional cohorts. This is a workflow demonstration, not certified actuarial methodology. | C2: A baseline-versus-adverse calculation across 300 fictional cohorts. This is a workflow demonstration, not certified actuarial methodology. | D2: A baseline-versus-adverse calculation across 300 fictional cohorts. This is a workflow demonstration, not certified actuarial methodology.
A4: Business result | B4: Value | C4: Unit | D4: Interpretation
A5: Baseline technical provisions | B5: =ROUND(SUM('Base Scenario'!$G$4:$G$303),Assumptions!$B$10) -> 11411088 | C5: EUR | D5: Calculated using baseline claims, inflation and discount assumptions.
A6: Adverse technical provisions | B6: =ROUND(SUM('Adverse Scenario'!$G$4:$G$303),Assumptions!$B$10) -> 13741242 | C6: EUR | D6: Calculated using adverse claims, inflation and discount assumptions.
A7: Increase in technical provisions | B7: =ROUND(B6-B5,Assumptions!$B$10) -> 2330154.1 | C7: EUR | D7: Additional reserve requirement under the adverse scenario.
A8: Baseline available own funds | B8: =ROUND(Assumptions!$B$8-B5,Assumptions!$B$10) -> 63588912 | C8: EUR | D8: Synthetic resources less baseline technical provisions.
A9: Adverse available own funds | B9: =ROUND(Assumptions!$B$8-B6,Assumptions!$B$10) -> 61258758 | C9: EUR | D9: Synthetic resources less adverse technical provisions.
A10: Reduction in available own funds | B10: =ROUND(B8-B9,Assumptions!$B$10) -> 2330154.1 | C10: EUR | D10: Direct effect of the additional technical provisions.
A11: Solvency Capital Requirement | B11: =Assumptions!$B$9 -> 35000000 | C11: EUR | D11: Fixed synthetic SCR used for the comparison.
A12: Baseline solvency ratio | B12: =ROUND(B8/B11,Assumptions!$B$15) -> 1.8168 | C12: % | D12: Baseline available own funds divided by SCR.
A13: Adverse solvency ratio | B13: =ROUND(B9/B11,Assumptions!$B$15) -> 1.7503 | C13: % | D13: Adverse available own funds divided by SCR.
A14: Solvency ratio deterioration | B14: =ROUND(B12-B13,Assumptions!$B$15) -> 0.0665 | C14: percentage points | D14: Difference between baseline and adverse ratios.
A16: Gate 2 accounting outputs | B16: Cell | C16: Expected signed value | D16: Reference
A17: Base technical provisions | B17: Accounting Bridge!C4 | C17: -11411088 | D17: Synthetic Q4 trial balance account 2200
A18: Base available own funds | B18: Accounting Bridge!C5 | C18: 63588912 | D18: Synthetic Q4 trial balance account 1100

Sheet Accounting Bridge
A1: Accounting outputs for external reconciliation | B1: Accounting outputs for external reconciliation | C1: Accounting outputs for external reconciliation
A2: Credits are negative and debits are positive. All figures are synthetic. | B2: Credits are negative and debits are positive. All figures are synthetic. | C2: Credits are negative and debits are positive. All figures are synthetic.
A3: Account | B3: Authoritative output | C3: Signed balance (EUR)
A4: 2200 | B4: Base technical provisions | C4: =-'Impact Summary'!B5 -> -11411088
A5: 1100 | B5: Base available own funds | C5: ='Impact Summary'!B8 -> 63588912
A6: CTRL | B6: Signed reference control total | C6: =SUM(C4:C5) -> 52177825

Sheet Assumptions
A1: Synthetic baseline and adverse assumptions | B1: Synthetic baseline and adverse assumptions | C1: Synthetic baseline and adverse assumptions | D1: Synthetic baseline and adverse assumptions | E1: Synthetic baseline and adverse assumptions | F1: Synthetic baseline and adverse assumptions | G1: Synthetic baseline and adverse assumptions | H1: Synthetic baseline and adverse assumptions | I1: Synthetic baseline and adverse assumptions | J1: Synthetic baseline and adverse assumptions
A3: Assumption | B3: Baseline | C3: Adverse | D3: Use | E3: Formula helper | F3: Calculated value | H3: Product | I3: Baseline factor | J3: Adverse factor
A4: Claims inflation | B4: 0.02 | C4: 0.055 | D4: Projected outstanding claims | E4: Baseline inflation multiplier | F4: =1+B4 -> 1.02 | H4: Motor | I4: 1.02 | J4: 1.12
A5: Discount rate | B5: 0.03 | C5: 0.015 | D5: Present-value calculation | E5: Adverse inflation multiplier | F5: =1+C4 -> 1.055 | H5: Property | I5: 1.04 | J5: 1.15
A6: Expense loading | B6: 0.025 | C6: 0.035 | D6: Claims handling expense | E6: Baseline discount divisor | F6: =1+B5 -> 1.03 | H6: Liability | I6: 1.06 | J6: 1.18
A7: Risk margin rate | B7: 0.04 | C7: 0.055 | D7: Synthetic risk margin | E7: Adverse discount divisor | F7: =1+C5 -> 1.015
A8: Resources before technical provisions | B8: 75000000 | D8: Own-funds comparison
A9: Solvency Capital Requirement | B9: 35000000 | D9: Solvency ratio denominator
A10: Currency precision | B10: 2 | D10: ROUND precision
A11: Exposure unit | B11: 100000 | D11: INT calculation
A12: Reporting significance | B12: 100 | D12: CEILING and FLOOR controls
A13: Fallback zero | B13: 0 | D13: Inactive cohorts
A15: Ratio precision | B15: 4 | C15: Displayed ratio calculation
A16: Active status | B16: Active | C16: Cohort inclusion criterion

Sheet Base Scenario
A1: Baseline cohort calculation | B1: Baseline cohort calculation | C1: Baseline cohort calculation | D1: Baseline cohort calculation | E1: Baseline cohort calculation | F1: Baseline cohort calculation | G1: Baseline cohort calculation | H1: Baseline cohort calculation | I1: Baseline cohort calculation | J1: Baseline cohort calculation | K1: Baseline cohort calculation | L1: Baseline cohort calculation | M1: Baseline cohort calculation
A2: Amounts in EUR for 2025-Q4 | B2: Amounts in EUR for 2025-Q4 | C2: Amounts in EUR for 2025-Q4 | D2: Amounts in EUR for 2025-Q4 | E2: Amounts in EUR for 2025-Q4 | F2: Amounts in EUR for 2025-Q4 | G2: Amounts in EUR for 2025-Q4 | H2: Amounts in EUR for 2025-Q4 | I2: Amounts in EUR for 2025-Q4 | J2: Amounts in EUR for 2025-Q4 | K2: Amounts in EUR for 2025-Q4 | L2: Amounts in EUR for 2025-Q4 | M2: Amounts in EUR for 2025-Q4
A3: Cohort ID | B3: Projected outstanding | C3: Expense | D3: Undiscounted requirement | E3: Best estimate liability | F3: Risk margin | G3: Technical provisions | H3: Change from opening | I3: Ceiling control | J3: Floor control | K3: Rounded up | L3: Rounded down | M3: Whole exposure units
A4: SYN-0001 | B4: =IF('Cohort Data'!D4=Assumptions!$B$16,ROUND('Cohort Data'!L4*'Cohort Data'!J4*Assumptions!$F$4,Assumptions!$B$10),Assumptions!$B$13) -> 26973.41 | C4: =IF('Cohort Data'!D4=Assumptions!$B$16,ROUND('Cohort Data'!E4*Assumptions!$B$6,Assumptions!$B$10),Assumptions!$B$13) -> 3725 | D4: =SUM(B4:C4) -> 30698.41 | E4: =ROUND(D4/Assumptions!$F$6,Assumptions!$B$10) -> 29804.28 | F4: =ROUND(E4*Assumptions!$B$7,Assumptions!$B$10) -> 1192.17 | G4: =SUM(E4:F4) -> 30996.45 | H4: =ROUND(G4-'Cohort Data'!H4,Assumptions!$B$10) -> 6626.01 | I4: =CEILING(G4,Assumptions!$B$12) -> 31000 | J4: =FLOOR(G4,Assumptions!$B$12) -> 30900 | K4: =ROUNDUP(G4,Assumptions!$B$10) -> 30996.45 | L4: =ROUNDDOWN(G4,Assumptions!$B$10) -> 30996.44 | M4: =INT('Cohort Data'!E4/Assumptions!$B$11) -> 1
A5: SYN-0002 | B5: =IF('Cohort Data'!D5=Assumptions!$B$16,ROUND('Cohort Data'!L5*'Cohort Data'!J5*Assumptions!$F$4,Assumptions!$B$10),Assumptions!$B$13) -> 34194.25 | C5: =IF('Cohort Data'!D5=Assumptions!$B$16,ROUND('Cohort Data'!E5*Assumptions!$B$6,Assumptions!$B$10),Assumptions!$B$13) -> 5550 | D5: =SUM(B5:C5) -> 39744.25 | E5: =ROUND(D5/Assumptions!$F$6,Assumptions!$B$10) -> 38586.65 | F5: =ROUND(E5*Assumptions!$B$7,Assumptions!$B$10) -> 1543.47 | G5: =SUM(E5:F5) -> 40130.12 | H5: =ROUND(G5-'Cohort Data'!H5,Assumptions!$B$10) -> 9507.44 | I5: =CEILING(G5,Assumptions!$B$12) -> 40200 | J5: =FLOOR(G5,Assumptions!$B$12) -> 40100 | K5: =ROUNDUP(G5,Assumptions!$B$10) -> 40130.12 | L5: =ROUNDDOWN(G5,Assumptions!$B$10) -> 40130.12 | M5: =INT('Cohort Data'!E5/Assumptions!$B$11) -> 2
A6: SYN-0003 | B6: =IF('Cohort Data'!D6=Assumptions!$B$16,ROUND('Cohort Data'!L6*'Cohort Data'!J6*Assumptions!$F$4,Assumptions!$B$10),Assumptions!$B$13) -> 10618.25 | C6: =IF('Cohort Data'!D6=Assumptions!$B$16,ROUND('Cohort Data'!E6*Assumptions!$B$6,Assumptions!$B$10),Assumptions!$B$13) -> 1550 | D6: =SUM(B6:C6) -> 12168.25 | E6: =ROUND(D6/Assumptions!$F$6,Assumptions!$B$10) -> 11813.83 | F6: =ROUND(E6*Assumptions!$B$7,Assumptions!$B$10) -> 472.55 | G6: =SUM(E6:F6) -> 12286.38 | H6: =ROUND(G6-'Cohort Data'!H6,Assumptions!$B$10) -> 2662 | I6: =CEILING(G6,Assumptions!$B$12) -> 12300 | J6: =FLOOR(G6,Assumptions!$B$12) -> 12200 | K6: =ROUNDUP(G6,Assumptions!$B$10) -> 12286.38 | L6: =ROUNDDOWN(G6,Assumptions!$B$10) -> 12286.38 | M6: =INT('Cohort Data'!E6/Assumptions!$B$11) -> 0
A7: SYN-0004 | B7: =IF('Cohort Data'!D7=Assumptions!$B$16,ROUND('Cohort Data'!L7*'Cohort Data'!J7*Assumptions!$F$4,Assumptions!$B$10),Assumptions!$B$13) -> 40007.54 | C7: =IF('Cohort Data'!D7=Assumptions!$B$16,ROUND('Cohort Data'!E7*Assumptions!$B$6,Assumptions!$B$10),Assumptions!$B$13) -> 5525 | D7: =SUM(B7:C7) -> 45532.54 | E7: =ROUND(D7/Assumptions!$F$6,Assumptions!$B$10) -> 44206.35 | F7: =ROUND(E7*Assumptions!$B$7,Assumptions!$B$10) -> 1768.25 | G7: =SUM(E7:F7) -> 45974.6 | H7: =ROUND(G7-'Cohort Data'!H7,Assumptions!$B$10) -> 10596.92 | I7: =CEILING(G7,Assumptions!$B$12) -> 46000 | J7: =FLOOR(G7,Assumptions!$B$12) -> 45900 | K7: =ROUNDUP(G7,Assumptions!$B$10) -> 45974.6 | L7: =ROUNDDOWN(G7,Assumptions!$B$10) -> 45974.6 | M7: =INT('Cohort Data'!E7/Assumptions!$B$11) -> 2
A8: SYN-0005 | B8: =IF('Cohort Data'!D8=Assumptions!$B$16,ROUND('Cohort Data'!L8*'Cohort Data'!J8*Assumptions!$F$4,Assumptions!$B$10),Assumptions!$B$13) -> 64397.77 | C8: =IF('Cohort Data'!D8=Assumptions!$B$16,ROUND('Cohort Data'!E8*Assumptions!$B$6,Assumptions!$B$10),Assumptions!$B$13) -> 5475 | D8: =SUM(B8:C8) -> 69872.77 | E8: =ROUND(D8/Assumptions!$F$6,Assumptions!$B$10) -> 67837.64 | F8: =ROUND(E8*Assumptions!$B$7,Assumptions!$B$10) -> 2713.51 | G8: =SUM(E8:F8) -> 70551.15 | H8: =ROUND(G8-'Cohort Data'!H8,Assumptions!$B$10) -> 9844.35 | I8: =CEILING(G8,Assumptions!$B$12) -> 70600 | J8: =FLOOR(G8,Assumptions!$B$12) -> 70500 | K8: =ROUNDUP(G8,Assumptions!$B$10) -> 70551.15 | L8: =ROUNDDOWN(G8,Assumptions!$B$10) -> 70551.15 | M8: =INT('Cohort Data'!E8/Assumptions!$B$11) -> 2
A9: SYN-0006 | B9: =IF('Cohort Data'!D9=Assumptions!$B$16,ROUND('Cohort Data'!L9*'Cohort Data'!J9*Assumptions!$F$4,Assumptions!$B$10),Assumptions!$B$13) -> 51020.53 | C9: =IF('Cohort Data'!D9=Assumptions!$B$16,ROUND('Cohort Data'!E9*Assumptions!$B$6,Assumptions!$B$10),Assumptions!$B$13) -> 5650 | D9: =SUM(B9:C9) -> 56670.53 | E9: =ROUND(D9/Assumptions!$F$6,Assumptions!$B$10) -> 55019.93 | F9: =ROUND(E9*Assumptions!$B$7,Assumptions!$B$10) -> 2200.8 | G9: =SUM(E9:F9) -> 57220.73 | H9: =ROUND(G9-'Cohort Data'!H9,Assumptions!$B$10) -> 10503.82 | I9: =CEILING(G9,Assumptions!$B$12) -> 57300 | J9: =FLOOR(G9,Assumptions!$B$12) -> 57200 | K9: =ROUNDUP(G9,Assumptions!$B$10) -> 57220.73 | L9: =ROUNDDOWN(G9,Assumptions!$B$10) -> 57220.73 | M9: =INT('Cohort Data'!E9/Assumptions!$B$11) -> 2
A10: SYN-0007 | B10: =IF('Cohort Data'!D10=Assumptions!$B$16,ROUND('Cohort Data'!L10*'Cohort Data'!J10*Assumptions!$F$4,Assumptions!$B$10),Assumptions!$B$13) -> 18682.25 | C10: =IF('Cohort Data'!D10=Assumptions!$B$16,ROUND('Cohort Data'!E10*Assumptions!$B$6,Assumptions!$B$10),Assumptions!$B$13) -> 3225 | D10: =SUM(B10:C10) -> 21907.25 | E10: =ROUND(D10/Assumptions!$F$6,Assumptions!$B$10) -> 21269.17 | F10: =ROUND(E10*Assumptions!$B$7,Assumptions!$B$10) -> 850.77 | G10: =SUM(E10:F10) -> 22119.94 | H10: =ROUND(G10-'Cohort Data'!H10,Assumptions!$B$10) -> 4881.41 | I10: =CEILING(G10,Assumptions!$B$12) -> 22200 | J10: =FLOOR(G10,Assumptions!$B$12) -> 22100 | K10: =ROUNDUP(G10,Assumptions!$B$10) -> 22119.94 | L10: =ROUNDDOWN(G10,Assumptions!$B$10) -> 22119.94 | M10: =INT('Cohort Data'!E10/Assumptions!$B$11) -> 1
A11: SYN-0008 | B11: =IF('Cohort Data'!D11=Assumptions!$B$16,ROUND('Cohort Data'!L11*'Cohort Data'!J11*Assumptions!$F$4,Assumptions!$B$10),Assumptions!$B$13) -> 17559.21 | C11: =IF('Cohort Data'!D11=Assumptions!$B$16,ROUND('Cohort Data'!E11*Assumptions!$B$6,Assumptions!$B$10),Assumptions!$B$13) -> 2850 | D11: =SUM(B11:C11) -> 20409.21 | E11: =ROUND(D11/Assumptions!$F$6,Assumptions!$B$10) -> 19814.77 | F11: =ROUND(E11*Assumptions!$B$7,Assumptions!$B$10) -> 792.59 | G11: =SUM(E11:F11) -> 20607.36 | H11: =ROUND(G11-'Cohort Data'!H11,Assumptions!$B$10) -> 4551.14 | I11: =CEILING(G11,Assumptions!$B$12) -> 20700 | J11: =FLOOR(G11,Assumptions!$B$12) -> 20600 | K11: =ROUNDUP(G11,Assumptions!$B$10) -> 20607.36 | L11: =ROUNDDOWN(G11,Assumptions!$B$10) -> 20607.36 | M11: =INT('Cohort Data'!E11/Assumptions!$B$11) -> 1
A12: SYN-0009 | B12: =IF('Cohort Data'!D12=Assumptions!$B$16,ROUND('Cohort Data'!L12*'Cohort Data'!J12*Assumptions!$F$4,Assumptions!$B$10),Assumptions!$B$13) -> 39904.06 | C12: =IF('Cohort Data'!D12=Assumptions!$B$16,ROUND('Cohort Data'!E12*Assumptions!$B$6,Assumptions!$B$10),Assumptions!$B$13) -> 5825 | D12: =SUM(B12:C12) -> 45729.06 | E12: =ROUND(D12/Assumptions!$F$6,Assumptions!$B$10) -> 44397.15 | F12: =ROUND(E12*Assumptions!$B$7,Assumptions!$B$10) -> 1775.89 | G12: =SUM(E12:F12) -> 46173.04 | H12: =ROUND(G12-'Cohort Data'!H12,Assumptions!$B$10) -> 11849.34 | I12: =CEILING(G12,Assumptions!$B$12) -> 46200 | J12: =FLOOR(G12,Assumptions!$B$12) -> 46100 | K12: =ROUNDUP(G12,Assumptions!$B$10) -> 46173.04 | L12: =ROUNDDOWN(G12,Assumptions!$B$10) -> 46173.04 | M12: =INT('Cohort Data'!E12/Assumptions!$B$11) -> 2
A13: SYN-0010 | B13: =IF('Cohort Data'!D13=Assumptions!$B$16,ROUND('Cohort Data'!L13*'Cohort Data'!J13*Assumptions!$F$4,Assumptions!$B$10),Assumptions!$B$13) -> 10487.65 | C13: =IF('Cohort Data'!D13=Assumptions!$B$16,ROUND('Cohort Data'!E13*Assumptions!$B$6,Assumptions!$B$10),Assumptions!$B$13) -> 1975 | D13: =SUM(B13:C13) -> 12462.65 | E13: =ROUND(D13/Assumptions!$F$6,Assumptions!$B$10) -> 12099.66 | F13: =ROUND(E13*Assumptions!$B$7,Assumptions!$B$10) -> 483.99 | G13: =SUM(E13:F13) -> 12583.65 | H13: =ROUND(G13-'Cohort Data'!H13,Assumptions!$B$10) -> 3108.07 | I13: =CEILING(G13,Assumptions!$B$12) -> 12600 | J13: =FLOOR(G13,Assumptions!$B$12) -> 12500 | K13: =ROUNDUP(G13,Assumptions!$B$10) -> 12583.65 | L13: =ROUNDDOWN(G13,Assumptions!$B$10) -> 12583.65 | M13: =INT('Cohort Data'!E13/Assumptions!$B$11) -> 0
A14: SYN-0011 | B14: =IF('Cohort Data'!D14=Assumptions!$B$16,ROUND('Cohort Data'!L14*'Cohort Data'!J14*Assumptions!$F$4,Assumptions!$B$10),Assumptions!$B$13) -> 46789.55 | C14: =IF('Cohort Data'!D14=Assumptions!$B$16,ROUND('Cohort Data'!E14*Assumptions!$B$6,Assumptions!$B$10),Assumptions!$B$13) -> 4075 | D14: =SUM(B14:C14) -> 50864.55 | E14: =ROUND(D14/Assumptions!$F$6,Assumptions!$B$10) -> 49383.06 | F14: =ROUND(E14*Assumptions!$B$7,Assumptions!$B$10) -> 1975.32 | G14: =SUM(E14:F14) -> 51358.38 | H14: =ROUND(G14-'Cohort Data'!H14,Assumptions!$B$10) -> 9455.97 | I14: =CEILING(G14,Assumptions!$B$12) -> 51400 | J14: =FLOOR(G14,Assumptions!$B$12) -> 51300 | K14: =ROUNDUP(G14,Assumptions!$B$10) -> 51358.38 | L14: =ROUNDDOWN(G14,Assumptions!$B$10) -> 51358.38 | M14: =INT('Cohort Data'!E14/Assumptions!$B$11) -> 1
A15: SYN-0012 | B15: =IF('Cohort Data'!D15=Assumptions!$B$16,ROUND('Cohort Data'!L15*'Cohort Data'!J15*Assumptions!$F$4,Assumptions!$B$10),Assumptions!$B$13) -> 14323.74 | C15: =IF('Cohort Data'!D15=Assumptions!$B$16,ROUND('Cohort Data'!E15*Assumptions!$B$6,Assumptions!$B$10),Assumptions!$B$13) -> 2300 | D15: =SUM(B15:C15) -> 16623.74 | E15: =ROUND(D15/Assumptions!$F$6,Assumptions!$B$10) -> 16139.55 | F15: =ROUND(E15*Assumptions!$B$7,Assumptions!$B$10) -> 645.58 | G15: =SUM(E15:F15) -> 16785.13 | H15: =ROUND(G15-'Cohort Data'!H15,Assumptions!$B$10) -> 4464.49 | I15: =CEILING(G15,Assumptions!$B$12) -> 16800 | J15: =FLOOR(G15,Assumptions!$B$12) -> 16700 | K15: =ROUNDUP(G15,Assumptions!$B$10) -> 16785.13 | L15: =ROUNDDOWN(G15,Assumptions!$B$10) -> 16785.13 | M15: =INT('Cohort Data'!E15/Assumptions!$B$11) -> 0
... A303: SYN-0300 | B303: =IF('Cohort Data'!D303=Assumptions!$B$16,ROUND('Cohort Data'!L303*'Cohort Data'!J303*Assumptions!$F$4,Assumptions!$B$10),Assumptions!$B$13) -> 32096.07 | C303: =IF('Cohort Data'!D303=Assumptions!$B$16,ROUND('Cohort Data'!E303*Assumptions!$B$6,Assumptions!$B$10),Assumptions!$B$13) -> 3325 | D303: =SUM(B303:C303) -> 35421.07 | E303: =ROUND(D303/Assumptions!$F$6,Assumptions!$B$10) -> 34389.39 | F303: =ROUND(E303*Assumptions!$B$7,Assumptions!$B$10) -> 1375.58 | G303: =SUM(E303:F303) -> 35764.97 | H303: =ROUND(G303-'Cohort Data'!H303,Assumptions!$B$10) -> 7266.79 | I303: =CEILING(G303,Assumptions!$B$12) -> 35800 | J303: =FLOOR(G303,Assumptions!$B$12) -> 35700 | K303: =ROUNDUP(G303,Assumptions!$B$10) -> 35764.97 | L303: =ROUNDDOWN(G303,Assumptions!$B$10) -> 35764.97 | M303: =INT('Cohort Data'!E303/Assumptions!$B$11) -> 1

Sheet Adverse Scenario
A1: Adverse cohort calculation | B1: Adverse cohort calculation | C1: Adverse cohort calculation | D1: Adverse cohort calculation | E1: Adverse cohort calculation | F1: Adverse cohort calculation | G1: Adverse cohort calculation | H1: Adverse cohort calculation | I1: Adverse cohort calculation | J1: Adverse cohort calculation | K1: Adverse cohort calculation | L1: Adverse cohort calculation | M1: Adverse cohort calculation
A2: Amounts in EUR for 2025-Q4 | B2: Amounts in EUR for 2025-Q4 | C2: Amounts in EUR for 2025-Q4 | D2: Amounts in EUR for 2025-Q4 | E2: Amounts in EUR for 2025-Q4 | F2: Amounts in EUR for 2025-Q4 | G2: Amounts in EUR for 2025-Q4 | H2: Amounts in EUR for 2025-Q4 | I2: Amounts in EUR for 2025-Q4 | J2: Amounts in EUR for 2025-Q4 | K2: Amounts in EUR for 2025-Q4 | L2: Amounts in EUR for 2025-Q4 | M2: Amounts in EUR for 2025-Q4
A3: Cohort ID | B3: Projected outstanding | C3: Expense | D3: Undiscounted requirement | E3: Best estimate liability | F3: Risk margin | G3: Technical provisions | H3: Change from opening | I3: Ceiling control | J3: Floor control | K3: Rounded up | L3: Rounded down | M3: Whole exposure units
A4: SYN-0001 | B4: =IF('Cohort Data'!D4=Assumptions!$B$16,ROUND('Cohort Data'!L4*'Cohort Data'!K4*Assumptions!$F$5,Assumptions!$B$10),Assumptions!$B$13) -> 30634.16 | C4: =IF('Cohort Data'!D4=Assumptions!$B$16,ROUND('Cohort Data'!E4*Assumptions!$C$6,Assumptions!$B$10),Assumptions!$B$13) -> 5215 | D4: =SUM(B4:C4) -> 35849.16 | E4: =ROUND(D4/Assumptions!$F$7,Assumptions!$B$10) -> 35319.37 | F4: =ROUND(E4*Assumptions!$C$7,Assumptions!$B$10) -> 1942.57 | G4: =SUM(E4:F4) -> 37261.94 | H4: =ROUND(G4-'Cohort Data'!H4,Assumptions!$B$10) -> 12891.5 | I4: =CEILING(G4,Assumptions!$B$12) -> 37300 | J4: =FLOOR(G4,Assumptions!$B$12) -> 37200 | K4: =ROUNDUP(G4,Assumptions!$B$10) -> 37261.94 | L4: =ROUNDDOWN(G4,Assumptions!$B$10) -> 37261.94 | M4: =INT('Cohort Data'!E4/Assumptions!$B$11) -> 1
A5: SYN-0002 | B5: =IF('Cohort Data'!D5=Assumptions!$B$16,ROUND('Cohort Data'!L5*'Cohort Data'!K5*Assumptions!$F$5,Assumptions!$B$10),Assumptions!$B$13) -> 39108.39 | C5: =IF('Cohort Data'!D5=Assumptions!$B$16,ROUND('Cohort Data'!E5*Assumptions!$C$6,Assumptions!$B$10),Assumptions!$B$13) -> 7770 | D5: =SUM(B5:C5) -> 46878.39 | E5: =ROUND(D5/Assumptions!$F$7,Assumptions!$B$10) -> 46185.61 | F5: =ROUND(E5*Assumptions!$C$7,Assumptions!$B$10) -> 2540.21 | G5: =SUM(E5:F5) -> 48725.82 | H5: =ROUND(G5-'Cohort Data'!H5,Assumptions!$B$10) -> 18103.14 | I5: =CEILING(G5,Assumptions!$B$12) -> 48800 | J5: =FLOOR(G5,Assumptions!$B$12) -> 48700 | K5: =ROUNDUP(G5,Assumptions!$B$10) -> 48725.82 | L5: =ROUNDDOWN(G5,Assumptions!$B$10) -> 48725.82 | M5: =INT('Cohort Data'!E5/Assumptions!$B$11) -> 2
A6: SYN-0003 | B6: =IF('Cohort Data'!D6=Assumptions!$B$16,ROUND('Cohort Data'!L6*'Cohort Data'!K6*Assumptions!$F$5,Assumptions!$B$10),Assumptions!$B$13) -> 12225.91 | C6: =IF('Cohort Data'!D6=Assumptions!$B$16,ROUND('Cohort Data'!E6*Assumptions!$C$6,Assumptions!$B$10),Assumptions!$B$13) -> 2170 | D6: =SUM(B6:C6) -> 14395.91 | E6: =ROUND(D6/Assumptions!$F$7,Assumptions!$B$10) -> 14183.16 | F6: =ROUND(E6*Assumptions!$C$7,Assumptions!$B$10) -> 780.07 | G6: =SUM(E6:F6) -> 14963.23 | H6: =ROUND(G6-'Cohort Data'!H6,Assumptions!$B$10) -> 5338.85 | I6: =CEILING(G6,Assumptions!$B$12) -> 15000 | J6: =FLOOR(G6,Assumptions!$B$12) -> 14900 | K6: =ROUNDUP(G6,Assumptions!$B$10) -> 14963.23 | L6: =ROUNDDOWN(G6,Assumptions!$B$10) -> 14963.23 | M6: =INT('Cohort Data'!E6/Assumptions!$B$11) -> 0
A7: SYN-0004 | B7: =IF('Cohort Data'!D7=Assumptions!$B$16,ROUND('Cohort Data'!L7*'Cohort Data'!K7*Assumptions!$F$5,Assumptions!$B$10),Assumptions!$B$13) -> 45437.25 | C7: =IF('Cohort Data'!D7=Assumptions!$B$16,ROUND('Cohort Data'!E7*Assumptions!$C$6,Assumptions!$B$10),Assumptions!$B$13) -> 7735 | D7: =SUM(B7:C7) -> 53172.25 | E7: =ROUND(D7/Assumptions!$F$7,Assumptions!$B$10) -> 52386.45 | F7: =ROUND(E7*Assumptions!$C$7,Assumptions!$B$10) -> 2881.25 | G7: =SUM(E7:F7) -> 55267.7 | H7: =ROUND(G7-'Cohort Data'!H7,Assumptions!$B$10) -> 19890.02 | I7: =CEILING(G7,Assumptions!$B$12) -> 55300 | J7: =FLOOR(G7,Assumptions!$B$12) -> 55200 | K7: =ROUNDUP(G7,Assumptions!$B$10) -> 55267.7 | L7: =ROUNDDOWN(G7,Assumptions!$B$10) -> 55267.7 | M7: =INT('Cohort Data'!E7/Assumptions!$B$11) -> 2
A8: SYN-0005 | B8: =IF('Cohort Data'!D8=Assumptions!$B$16,ROUND('Cohort Data'!L8*'Cohort Data'!K8*Assumptions!$F$5,Assumptions!$B$10),Assumptions!$B$13) -> 73652.53 | C8: =IF('Cohort Data'!D8=Assumptions!$B$16,ROUND('Cohort Data'!E8*Assumptions!$C$6,Assumptions!$B$10),Assumptions!$B$13) -> 7665 | D8: =SUM(B8:C8) -> 81317.53 | E8: =ROUND(D8/Assumptions!$F$7,Assumptions!$B$10) -> 80115.79 | F8: =ROUND(E8*Assumptions!$C$7,Assumptions!$B$10) -> 4406.37 | G8: =SUM(E8:F8) -> 84522.16 | H8: =ROUND(G8-'Cohort Data'!H8,Assumptions!$B$10) -> 23815.36 | I8: =CEILING(G8,Assumptions!$B$12) -> 84600 | J8: =FLOOR(G8,Assumptions!$B$12) -> 84500 | K8: =ROUNDUP(G8,Assumptions!$B$10) -> 84522.16 | L8: =ROUNDDOWN(G8,Assumptions!$B$10) -> 84522.15 | M8: =INT('Cohort Data'!E8/Assumptions!$B$11) -> 2
A9: SYN-0006 | B9: =IF('Cohort Data'!D9=Assumptions!$B$16,ROUND('Cohort Data'!L9*'Cohort Data'!K9*Assumptions!$F$5,Assumptions!$B$10),Assumptions!$B$13) -> 58745.34 | C9: =IF('Cohort Data'!D9=Assumptions!$B$16,ROUND('Cohort Data'!E9*Assumptions!$C$6,Assumptions!$B$10),Assumptions!$B$13) -> 7910 | D9: =SUM(B9:C9) -> 66655.34 | E9: =ROUND(D9/Assumptions!$F$7,Assumptions!$B$10) -> 65670.29 | F9: =ROUND(E9*Assumptions!$C$7,Assumptions!$B$10) -> 3611.87 | G9: =SUM(E9:F9) -> 69282.16 | H9: =ROUND(G9-'Cohort Data'!H9,Assumptions!$B$10) -> 22565.25 | I9: =CEILING(G9,Assumptions!$B$12) -> 69300 | J9: =FLOOR(G9,Assumptions!$B$12) -> 69200 | K9: =ROUNDUP(G9,Assumptions!$B$10) -> 69282.16 | L9: =ROUNDDOWN(G9,Assumptions!$B$10) -> 69282.15 | M9: =INT('Cohort Data'!E9/Assumptions!$B$11) -> 2
A10: SYN-0007 | B10: =IF('Cohort Data'!D10=Assumptions!$B$16,ROUND('Cohort Data'!L10*'Cohort Data'!K10*Assumptions!$F$5,Assumptions!$B$10),Assumptions!$B$13) -> 21217.75 | C10: =IF('Cohort Data'!D10=Assumptions!$B$16,ROUND('Cohort Data'!E10*Assumptions!$C$6,Assumptions!$B$10),Assumptions!$B$13) -> 4515 | D10: =SUM(B10:C10) -> 25732.75 | E10: =ROUND(D10/Assumptions!$F$7,Assumptions!$B$10) -> 25352.46 | F10: =ROUND(E10*Assumptions!$C$7,Assumptions!$B$10) -> 1394.39 | G10: =SUM(E10:F10) -> 26746.85 | H10: =ROUND(G10-'Cohort Data'!H10,Assumptions!$B$10) -> 9508.32 | I10: =CEILING(G10,Assumptions!$B$12) -> 26800 | J10: =FLOOR(G10,Assumptions!$B$12) -> 26700 | K10: =ROUNDUP(G10,Assumptions!$B$10) -> 26746.85 | L10: =ROUNDDOWN(G10,Assumptions!$B$10) -> 26746.85 | M10: =INT('Cohort Data'!E10/Assumptions!$B$11) -> 1
A11: SYN-0008 | B11: =IF('Cohort Data'!D11=Assumptions!$B$16,ROUND('Cohort Data'!L11*'Cohort Data'!K11*Assumptions!$F$5,Assumptions!$B$10),Assumptions!$B$13) -> 20082.68 | C11: =IF('Cohort Data'!D11=Assumptions!$B$16,ROUND('Cohort Data'!E11*Assumptions!$C$6,Assumptions!$B$10),Assumptions!$B$13) -> 3990 | D11: =SUM(B11:C11) -> 24072.68 | E11: =ROUND(D11/Assumptions!$F$7,Assumptions!$B$10) -> 23716.93 | F11: =ROUND(E11*Assumptions!$C$7,Assumptions!$B$10) -> 1304.43 | G11: =SUM(E11:F11) -> 25021.36 | H11: =ROUND(G11-'Cohort Data'!H11,Assumptions!$B$10) -> 8965.14 | I11: =CEILING(G11,Assumptions!$B$12) -> 25100 | J11: =FLOOR(G11,Assumptions!$B$12) -> 25000 | K11: =ROUNDUP(G11,Assumptions!$B$10) -> 25021.36 | L11: =ROUNDDOWN(G11,Assumptions!$B$10) -> 25021.36 | M11: =INT('Cohort Data'!E11/Assumptions!$B$11) -> 1
A12: SYN-0009 | B12: =IF('Cohort Data'!D12=Assumptions!$B$16,ROUND('Cohort Data'!L12*'Cohort Data'!K12*Assumptions!$F$5,Assumptions!$B$10),Assumptions!$B$13) -> 45945.77 | C12: =IF('Cohort Data'!D12=Assumptions!$B$16,ROUND('Cohort Data'!E12*Assumptions!$C$6,Assumptions!$B$10),Assumptions!$B$13) -> 8155 | D12: =SUM(B12:C12) -> 54100.77 | E12: =ROUND(D12/Assumptions!$F$7,Assumptions!$B$10) -> 53301.25 | F12: =ROUND(E12*Assumptions!$C$7,Assumptions!$B$10) -> 2931.57 | G12: =SUM(E12:F12) -> 56232.82 | H12: =ROUND(G12-'Cohort Data'!H12,Assumptions!$B$10) -> 21909.12 | I12: =CEILING(G12,Assumptions!$B$12) -> 56300 | J12: =FLOOR(G12,Assumptions!$B$12) -> 56200 | K12: =ROUNDUP(G12,Assumptions!$B$10) -> 56232.82 | L12: =ROUNDDOWN(G12,Assumptions!$B$10) -> 56232.82 | M12: =INT('Cohort Data'!E12/Assumptions!$B$11) -> 2
A13: SYN-0010 | B13: =IF('Cohort Data'!D13=Assumptions!$B$16,ROUND('Cohort Data'!L13*'Cohort Data'!K13*Assumptions!$F$5,Assumptions!$B$10),Assumptions!$B$13) -> 11911 | C13: =IF('Cohort Data'!D13=Assumptions!$B$16,ROUND('Cohort Data'!E13*Assumptions!$C$6,Assumptions!$B$10),Assumptions!$B$13) -> 2765 | D13: =SUM(B13:C13) -> 14676 | E13: =ROUND(D13/Assumptions!$F$7,Assumptions!$B$10) -> 14459.11 | F13: =ROUND(E13*Assumptions!$C$7,Assumptions!$B$10) -> 795.25 | G13: =SUM(E13:F13) -> 15254.36 | H13: =ROUND(G13-'Cohort Data'!H13,Assumptions!$B$10) -> 5778.78 | I13: =CEILING(G13,Assumptions!$B$12) -> 15300 | J13: =FLOOR(G13,Assumptions!$B$12) -> 15200 | K13: =ROUNDUP(G13,Assumptions!$B$10) -> 15254.36 | L13: =ROUNDDOWN(G13,Assumptions!$B$10) -> 15254.36 | M13: =INT('Cohort Data'!E13/Assumptions!$B$11) -> 0
A14: SYN-0011 | B14: =IF('Cohort Data'!D14=Assumptions!$B$16,ROUND('Cohort Data'!L14*'Cohort Data'!K14*Assumptions!$F$5,Assumptions!$B$10),Assumptions!$B$13) -> 53513.79 | C14: =IF('Cohort Data'!D14=Assumptions!$B$16,ROUND('Cohort Data'!E14*Assumptions!$C$6,Assumptions!$B$10),Assumptions!$B$13) -> 5705 | D14: =SUM(B14:C14) -> 59218.79 | E14: =ROUND(D14/Assumptions!$F$7,Assumptions!$B$10) -> 58343.64 | F14: =ROUND(E14*Assumptions!$C$7,Assumptions!$B$10) -> 3208.9 | G14: =SUM(E14:F14) -> 61552.54 | H14: =ROUND(G14-'Cohort Data'!H14,Assumptions!$B$10) -> 19650.13 | I14: =CEILING(G14,Assumptions!$B$12) -> 61600 | J14: =FLOOR(G14,Assumptions!$B$12) -> 61500 | K14: =ROUNDUP(G14,Assumptions!$B$10) -> 61552.54 | L14: =ROUNDDOWN(G14,Assumptions!$B$10) -> 61552.54 | M14: =INT('Cohort Data'!E14/Assumptions!$B$11) -> 1
A15: SYN-0012 | B15: =IF('Cohort Data'!D15=Assumptions!$B$16,ROUND('Cohort Data'!L15*'Cohort Data'!K15*Assumptions!$F$5,Assumptions!$B$10),Assumptions!$B$13) -> 16492.44 | C15: =IF('Cohort Data'!D15=Assumptions!$B$16,ROUND('Cohort Data'!E15*Assumptions!$C$6,Assumptions!$B$10),Assumptions!$B$13) -> 3220 | D15: =SUM(B15:C15) -> 19712.44 | E15: =ROUND(D15/Assumptions!$F$7,Assumptions!$B$10) -> 19421.12 | F15: =ROUND(E15*Assumptions!$C$7,Assumptions!$B$10) -> 1068.16 | G15: =SUM(E15:F15) -> 20489.28 | H15: =ROUND(G15-'Cohort Data'!H15,Assumptions!$B$10) -> 8168.64 | I15: =CEILING(G15,Assumptions!$B$12) -> 20500 | J15: =FLOOR(G15,Assumptions!$B$12) -> 20400 | K15: =ROUNDUP(G15,Assumptions!$B$10) -> 20489.28 | L15: =ROUNDDOWN(G15,Assumptions!$B$10) -> 20489.28 | M15: =INT('Cohort Data'!E15/Assumptions!$B$11) -> 0
... A303: SYN-0300 | B303: =IF('Cohort Data'!D303=Assumptions!$B$16,ROUND('Cohort Data'!L303*'Cohort Data'!K303*Assumptions!$F$5,Assumptions!$B$10),Assumptions!$B$13) -> 36955.6 | C303: =IF('Cohort Data'!D303=Assumptions!$B$16,ROUND('Cohort Data'!E303*Assumptions!$C$6,Assumptions!$B$10),Assumptions!$B$13) -> 4655 | D303: =SUM(B303:C303) -> 41610.6 | E303: =ROUND(D303/Assumptions!$F$7,Assumptions!$B$10) -> 40995.67 | F303: =ROUND(E303*Assumptions!$C$7,Assumptions!$B$10) -> 2254.76 | G303: =SUM(E303:F303) -> 43250.43 | H303: =ROUND(G303-'Cohort Data'!H303,Assumptions!$B$10) -> 14752.25 | I303: =CEILING(G303,Assumptions!$B$12) -> 43300 | J303: =FLOOR(G303,Assumptions!$B$12) -> 43200 | K303: =ROUNDUP(G303,Assumptions!$B$10) -> 43250.43 | L303: =ROUNDDOWN(G303,Assumptions!$B$10) -> 43250.43 | M303: =INT('Cohort Data'!E303/Assumptions!$B$11) -> 1

Sheet Aggregation
A1: Product-level scenario comparison | B1: Product-level scenario comparison | C1: Product-level scenario comparison | D1: Product-level scenario comparison | E1: Product-level scenario comparison | F1: Product-level scenario comparison | G1: Product-level scenario comparison | H1: Product-level scenario comparison | I1: Product-level scenario comparison | J1: Product-level scenario comparison
A2: The portfolio total reconciles to the Impact Summary. | B2: The portfolio total reconciles to the Impact Summary. | C2: The portfolio total reconciles to the Impact Summary. | D2: The portfolio total reconciles to the Impact Summary. | E2: The portfolio total reconciles to the Impact Summary. | F2: The portfolio total reconciles to the Impact Summary. | G2: The portfolio total reconciles to the Impact Summary. | H2: The portfolio total reconciles to the Impact Summary. | I2: The portfolio total reconciles to the Impact Summary. | J2: The portfolio total reconciles to the Impact Summary.
A3: Product | B3: Cohort count | C3: Active count | D3: Baseline provisions | E3: Adverse provisions | F3: Average baseline | G3: Average adverse active | H3: Minimum adverse | I3: Maximum adverse | J3: Increase
A4: Motor | B4: =COUNTIF('Cohort Data'!$B$4:$B$303,A4) -> 100 | C4: =COUNTIFS('Cohort Data'!$B$4:$B$303,A4,'Cohort Data'!$D$4:$D$303,Assumptions!$B$16) -> 95 | D4: =SUMIF('Cohort Data'!$B$4:$B$303,A4,'Base Scenario'!$G$4:$G$303) -> 3165029.1 | E4: =SUMIFS('Adverse Scenario'!$G$4:$G$303,'Cohort Data'!$B$4:$B$303,A4,'Cohort Data'!$D$4:$D$303,Assumptions!$B$16) -> 3801248 | F4: =AVERAGEIF('Cohort Data'!$B$4:$B$303,A4,'Base Scenario'!$G$4:$G$303) -> 31650.291 | G4: =AVERAGEIFS('Adverse Scenario'!$G$4:$G$303,'Cohort Data'!$B$4:$B$303,A4,'Cohort Data'!$D$4:$D$303,Assumptions!$B$16) -> 40013.137 | H4: =_xlfn.MINIFS('Adverse Scenario'!$G$4:$G$303,'Cohort Data'!$B$4:$B$303,A4,'Cohort Data'!$D$4:$D$303,Assumptions!$B$16) -> 15254.36 | I4: =_xlfn.MAXIFS('Adverse Scenario'!$G$4:$G$303,'Cohort Data'!$B$4:$B$303,A4,'Cohort Data'!$D$4:$D$303,Assumptions!$B$16) -> 88101.03 | J4: =E4-D4 -> 636218.86
A5: Property | B5: =COUNTIF('Cohort Data'!$B$4:$B$303,A5) -> 100 | C5: =COUNTIFS('Cohort Data'!$B$4:$B$303,A5,'Cohort Data'!$D$4:$D$303,Assumptions!$B$16) -> 95 | D5: =SUMIF('Cohort Data'!$B$4:$B$303,A5,'Base Scenario'!$G$4:$G$303) -> 3880127.2 | E5: =SUMIFS('Adverse Scenario'!$G$4:$G$303,'Cohort Data'!$B$4:$B$303,A5,'Cohort Data'!$D$4:$D$303,Assumptions!$B$16) -> 4667852.6 | F5: =AVERAGEIF('Cohort Data'!$B$4:$B$303,A5,'Base Scenario'!$G$4:$G$303) -> 38801.272 | G5: =AVERAGEIFS('Adverse Scenario'!$G$4:$G$303,'Cohort Data'!$B$4:$B$303,A5,'Cohort Data'!$D$4:$D$303,Assumptions!$B$16) -> 49135.291 | H5: =_xlfn.MINIFS('Adverse Scenario'!$G$4:$G$303,'Cohort Data'!$B$4:$B$303,A5,'Cohort Data'!$D$4:$D$303,Assumptions!$B$16) -> 14640.17 | I5: =_xlfn.MAXIFS('Adverse Scenario'!$G$4:$G$303,'Cohort Data'!$B$4:$B$303,A5,'Cohort Data'!$D$4:$D$303,Assumptions!$B$16) -> 106791.58 | J5: =E5-D5 -> 787725.44
A6: Liability | B6: =COUNTIF('Cohort Data'!$B$4:$B$303,A6) -> 100 | C6: =COUNTIFS('Cohort Data'!$B$4:$B$303,A6,'Cohort Data'!$D$4:$D$303,Assumptions!$B$16) -> 95 | D6: =SUMIF('Cohort Data'!$B$4:$B$303,A6,'Base Scenario'!$G$4:$G$303) -> 4365931.3 | E6: =SUMIFS('Adverse Scenario'!$G$4:$G$303,'Cohort Data'!$B$4:$B$303,A6,'Cohort Data'!$D$4:$D$303,Assumptions!$B$16) -> 5272141.1 | F6: =AVERAGEIF('Cohort Data'!$B$4:$B$303,A6,'Base Scenario'!$G$4:$G$303) -> 43659.313 | G6: =AVERAGEIFS('Adverse Scenario'!$G$4:$G$303,'Cohort Data'!$B$4:$B$303,A6,'Cohort Data'!$D$4:$D$303,Assumptions!$B$16) -> 55496.222 | H6: =_xlfn.MINIFS('Adverse Scenario'!$G$4:$G$303,'Cohort Data'!$B$4:$B$303,A6,'Cohort Data'!$D$4:$D$303,Assumptions!$B$16) -> 14963.23 | I6: =_xlfn.MAXIFS('Adverse Scenario'!$G$4:$G$303,'Cohort Data'!$B$4:$B$303,A6,'Cohort Data'!$D$4:$D$303,Assumptions!$B$16) -> 109804.99 | J6: =E6-D6 -> 906209.8
A8: Portfolio total | B8: =SUM(B4:B6) -> 300 | C8: =SUM(C4:C6) -> 285 | D8: =SUM(D4:D6) -> 11411088 | E8: =SUM(E4:E6) -> 13741242 | J8: =SUM(J4:J6) -> 2330154.1

Sheet Cohort Data
A1: Synthetic cohort data and derived lookup fields | B1: Synthetic cohort data and derived lookup fields | C1: Synthetic cohort data and derived lookup fields | D1: Synthetic cohort data and derived lookup fields | E1: Synthetic cohort data and derived lookup fields | F1: Synthetic cohort data and derived lookup fields | G1: Synthetic cohort data and derived lookup fields | H1: Synthetic cohort data and derived lookup fields | I1: Synthetic cohort data and derived lookup fields | J1: Synthetic cohort data and derived lookup fields | K1: Synthetic cohort data and derived lookup fields | L1: Synthetic cohort data and derived lookup fields
A2: Aurora General Insurance SA; 2025-Q4; EUR. All 300 cohorts are fictional. | B2: Aurora General Insurance SA; 2025-Q4; EUR. All 300 cohorts are fictional. | C2: Aurora General Insurance SA; 2025-Q4; EUR. All 300 cohorts are fictional. | D2: Aurora General Insurance SA; 2025-Q4; EUR. All 300 cohorts are fictional. | E2: Aurora General Insurance SA; 2025-Q4; EUR. All 300 cohorts are fictional. | F2: Aurora General Insurance SA; 2025-Q4; EUR. All 300 cohorts are fictional. | G2: Aurora General Insurance SA; 2025-Q4; EUR. All 300 cohorts are fictional. | H2: Aurora General Insurance SA; 2025-Q4; EUR. All 300 cohorts are fictional. | I2: Aurora General Insurance SA; 2025-Q4; EUR. All 300 cohorts are fictional. | J2: Aurora General Insurance SA; 2025-Q4; EUR. All 300 cohorts are fictional. | K2: Aurora General Insurance SA; 2025-Q4; EUR. All 300 cohorts are fictional. | L2: Aurora General Insurance SA; 2025-Q4; EUR. All 300 cohorts are fictional.
A3: Cohort ID | B3: Product | C3: Region | D3: Active | E3: Premium | F3: Incurred claims | G3: Paid claims | H3: Opening reserve | I3: Product position | J3: Baseline factor | K3: Adverse factor | L3: Outstanding claims
A4: SYN-0001 | B4: Motor | C4: Belgium | D4: Active | E4: 149000 | F4: 86420 | G4: 60494 | H4: 24370.44 | I4: =MATCH(B4,Assumptions!$H$4:$H$6,0) -> 1 | J4: =INDEX(Assumptions!$I$4:$I$6,I4) -> 1.02 | K4: =VLOOKUP(B4,Assumptions!$H$4:$J$6,3,FALSE()) -> 1.12 | L4: =ABS(F4-G4) -> 25926
A5: SYN-0002 | B5: Property | C5: France | D5: Active | E5: 222000 | F5: 146520 | G5: 114285.6 | H5: 30622.68 | I5: =MATCH(B5,Assumptions!$H$4:$H$6,0) -> 2 | J5: =INDEX(Assumptions!$I$4:$I$6,I5) -> 1.04 | K5: =VLOOKUP(B5,Assumptions!$H$4:$J$6,3,FALSE()) -> 1.15 | L5: =ABS(F5-G5) -> 32234.4
A6: SYN-0003 | B6: Liability | C6: United Kingdom | D6: Active | E6: 62000 | F6: 44640 | G6: 34819.2 | H6: 9624.38 | I6: =MATCH(B6,Assumptions!$H$4:$H$6,0) -> 3 | J6: =INDEX(Assumptions!$I$4:$I$6,I6) -> 1.06 | K6: =VLOOKUP(B6,Assumptions!$H$4:$J$6,3,FALSE()) -> 1.18 | L6: =ABS(F6-G6) -> 9820.8
A7: SYN-0004 | B7: Motor | C7: Belgium | D7: Active | E7: 221000 | F7: 128180 | G7: 89726 | H7: 35377.68 | I7: =MATCH(B7,Assumptions!$H$4:$H$6,0) -> 1 | J7: =INDEX(Assumptions!$I$4:$I$6,I7) -> 1.02 | K7: =VLOOKUP(B7,Assumptions!$H$4:$J$6,3,FALSE()) -> 1.12 | L7: =ABS(F7-G7) -> 38454
A8: SYN-0005 | B8: Property | C8: France | D8: Active | E8: 219000 | F8: 144540 | G8: 83833.2 | H8: 60706.8 | I8: =MATCH(B8,Assumptions!$H$4:$H$6,0) -> 2 | J8: =INDEX(Assumptions!$I$4:$I$6,I8) -> 1.04 | K8: =VLOOKUP(B8,Assumptions!$H$4:$J$6,3,FALSE()) -> 1.15 | L8: =ABS(F8-G8) -> 60706.8
A9: SYN-0006 | B9: Liability | C9: United Kingdom | D9: Active | E9: 226000 | F9: 162720 | G9: 115531.2 | H9: 46716.91 | I9: =MATCH(B9,Assumptions!$H$4:$H$6,0) -> 3 | J9: =INDEX(Assumptions!$I$4:$I$6,I9) -> 1.06 | K9: =VLOOKUP(B9,Assumptions!$H$4:$J$6,3,FALSE()) -> 1.18 | L9: =ABS(F9-G9) -> 47188.8
A10: SYN-0007 | B10: Motor | C10: Belgium | D10: Active | E10: 129000 | F10: 74820 | G10: 56863.2 | H10: 17238.53 | I10: =MATCH(B10,Assumptions!$H$4:$H$6,0) -> 1 | J10: =INDEX(Assumptions!$I$4:$I$6,I10) -> 1.02 | K10: =VLOOKUP(B10,Assumptions!$H$4:$J$6,3,FALSE()) -> 1.12 | L10: =ABS(F10-G10) -> 17956.8
A11: SYN-0008 | B11: Property | C11: France | D11: Active | E11: 114000 | F11: 75240 | G11: 58687.2 | H11: 16056.22 | I11: =MATCH(B11,Assumptions!$H$4:$H$6,0) -> 2 | J11: =INDEX(Assumptions!$I$4:$I$6,I11) -> 1.04 | K11: =VLOOKUP(B11,Assumptions!$H$4:$J$6,3,FALSE()) -> 1.15 | L11: =ABS(F11-G11) -> 16552.8
A12: SYN-0009 | B12: Liability | C12: United Kingdom | D12: Active | E12: 233000 | F12: 167760 | G12: 130852.8 | H12: 34323.7 | I12: =MATCH(B12,Assumptions!$H$4:$H$6,0) -> 3 | J12: =INDEX(Assumptions!$I$4:$I$6,I12) -> 1.06 | K12: =VLOOKUP(B12,Assumptions!$H$4:$J$6,3,FALSE()) -> 1.18 | L12: =ABS(F12-G12) -> 36907.2
A13: SYN-0010 | B13: Motor | C13: Belgium | D13: Active | E13: 79000 | F13: 45820 | G13: 35739.6 | H13: 9475.58 | I13: =MATCH(B13,Assumptions!$H$4:$H$6,0) -> 1 | J13: =INDEX(Assumptions!$I$4:$I$6,I13) -> 1.02 | K13: =VLOOKUP(B13,Assumptions!$H$4:$J$6,3,FALSE()) -> 1.12 | L13: =ABS(F13-G13) -> 10080.4
A14: SYN-0011 | B14: Property | C14: France | D14: Active | E14: 163000 | F14: 107580 | G14: 63472.2 | H14: 41902.41 | I14: =MATCH(B14,Assumptions!$H$4:$H$6,0) -> 2 | J14: =INDEX(Assumptions!$I$4:$I$6,I14) -> 1.04 | K14: =VLOOKUP(B14,Assumptions!$H$4:$J$6,3,FALSE()) -> 1.15 | L14: =ABS(F14-G14) -> 44107.8
A15: SYN-0012 | B15: Liability | C15: United Kingdom | D15: Active | E15: 92000 | F15: 66240 | G15: 52992 | H15: 12320.64 | I15: =MATCH(B15,Assumptions!$H$4:$H$6,0) -> 3 | J15: =INDEX(Assumptions!$I$4:$I$6,I15) -> 1.06 | K15: =VLOOKUP(B15,Assumptions!$H$4:$J$6,3,FALSE()) -> 1.18 | L15: =ABS(F15-G15) -> 13248
... A303: SYN-0300 | B303: Liability | C303: United Kingdom | D303: Active | E303: 133000 | F303: 95760 | G303: 66074.4 | H303: 28498.18 | I303: =MATCH(B303,Assumptions!$H$4:$H$6,0) -> 3 | J303: =INDEX(Assumptions!$I$4:$I$6,I303) -> 1.06 | K303: =VLOOKUP(B303,Assumptions!$H$4:$J$6,3,FALSE()) -> 1.18 | L303: =ABS(F303-G303) -> 29685.6

Sheet Controls
A1: Independent workbook controls | B1: Independent workbook controls
A2: Every difference below should equal zero. | B2: Every difference below should equal zero.
A3: Control | B3: Difference
A4: Base provision bridge | B4: ='Accounting Bridge'!C4+'Impact Summary'!B5 -> 0
A5: Base own-funds bridge | B5: ='Accounting Bridge'!C5-'Impact Summary'!B8 -> 0
A6: Reserve increase equals own-funds reduction | B6: =ROUND('Impact Summary'!B7-'Impact Summary'!B10,Assumptions!$B$10) -> 0
A7: Product aggregation equals adverse total | B7: =ROUND(Aggregation!E8-'Impact Summary'!B6,Assumptions!$B$10) -> 0

Sheet Demo Guide
A1: Case 6 demonstration guide | B1: Case 6 demonstration guide | C1: Case 6 demonstration guide
A3: Scope | B3: Baseline-versus-adverse reserve calculation across 300 synthetic cohorts.
A4: Boundary | B4: This workbook does not implement or validate certified Solvency II or IFRS 17 methodology.
A5: Gate 1 context | B5: Aurora General Insurance SA; 2025-Q4; EUR; synthetic reserve stress demonstration.
A6: Gate 2 selection | B6: Select Accounting Bridge!C4 and Accounting Bridge!C5.
A7: Gate 3 | B7: Approve both one-to-one mappings and choose internal and external materiality thresholds.
A8: Gate 4 | B8: Create the named approval record before generating the PDF.
A9: Baseline | B9: The baseline technical provisions and own funds reconcile to the synthetic trial balance.
A10: Adverse impact | B10: The adverse scenario raises technical provisions, reduces own funds and lowers the solvency ratio.
A12: Business impact | B12: Expected value | C12: Cell
A13: Baseline technical provisions | B13: 11411088 | C13: Impact Summary!B5
A14: Adverse technical provisions | B14: 13741242 | C14: Impact Summary!B6
A15: Increase in technical provisions | B15: 2330154.1 | C15: Impact Summary!B7
A16: Reduction in available own funds | B16: 2330154.1 | C16: Impact Summary!B10
A17: Baseline solvency ratio | B17: 1.8168 | C17: Impact Summary!B12
A18: Solvency ratio deterioration | B18: 0.0665 | C18: Impact Summary!B14
