Workbook

Sheet Case Guide
A1: Case 8: Solvency II capital and dividend decision
A3: Business problem | B3: Synthetic Solvency II capital summary used in a management dividend discussion.
A4: Management floor | B4: 150% internal capital-management floor.
A5: Apparent decision | B5: The defective 162.2% ratio appears to support considering a EUR 10 million dividend.
A6: Correct comparison | B6: The approved-basis 146.3% ratio is below the management floor.
A7: Gate 2 output | B7: QRT Bridge!B4 (Final SCR only).
A8: Boundary | B8: Glass Box does not decide whether a dividend should be paid.
A9: Methodology boundary | B9: Glass Box does not validate Solvency II methodology.
A11: Manual check | B11: Expected value | C11: Location
A12: Approved Final SCR | B12: 123000000 | C12: Capital Summary!B9
A13: Workbook Final SCR | B13: 111000000 | C13: Capital Summary!C9
A14: Approved-basis ratio | B14: 1.463 | C14: Capital Summary!B10
A15: Workbook ratio | B15: 1.622 | C15: Capital Summary!C10
A16: External difference | B16: 12000000 | C16: Approved reference minus workbook SCR

Sheet Context
A1: Confirmed workbook context
A3: Field | B3: Workbook value
A4: Entity | B4: Glass Box Life Belgium SA
A5: Period | B5: 31 December 2025
A6: Currency | B6: EUR
A7: Basis | B7: Synthetic Solvency II capital demonstration
A8: Data status | B8: Entirely synthetic

Sheet Assumptions
A1: Approved capital assumptions
A3: Assumption | B3: Approved value | E3: SCR module | F3: Approved factor
A4: Diversification benefit | B4: 35000000 | E4: Market | F4: 1
A5: Operational risk | B5: 8000000 | E5: Life underwriting | F5: 1
A6: Internal capital-management floor | B6: 1.5 | E6: Counterparty | F6: 1
A7: Illustrative dividend | B7: 10000000 | E7: Other | F7: 1
A8: Included status | B8: Included

Sheet Own Funds
A1: Eligible own funds
A3: Component | B3: Amount (EUR) | C3: Eligibility
A4: Share capital and reserves | B4: 100000000 | C4: Included
A5: Retained earnings | B5: 80000000 | C5: Included
A7: Eligible own funds | B7: =SUM(B4:B5) -> 180000000

Sheet SCR Modules
A1: SCR modules before diversification
A3: Module | B3: Base SCR | C3: Approved factor | D3: Adjusted SCR | E3: Status
A4: Market | B4: 60000000 | C4: =VLOOKUP(A4,Assumptions!$E$4:$F$7,2,FALSE()) -> 1 | D4: =ROUND(B4*C4,0) -> 60000000 | E4: Included
A5: Life underwriting | B5: 50000000 | C5: =VLOOKUP(A5,Assumptions!$E$4:$F$7,2,FALSE()) -> 1 | D5: =ROUND(B5*C5,0) -> 50000000 | E5: Included
A6: Counterparty | B6: 25000000 | C6: =VLOOKUP(A6,Assumptions!$E$4:$F$7,2,FALSE()) -> 1 | D6: =ROUND(B6*C6,0) -> 25000000 | E6: Included
A7: Other | B7: 15000000 | C7: =VLOOKUP(A7,Assumptions!$E$4:$F$7,2,FALSE()) -> 1 | D7: =ROUND(B7*C7,0) -> 15000000 | E7: Included
A9: SCR before diversification | D9: =SUMIFS(D4:D7,E4:E7,Assumptions!$B$8) -> 150000000

Sheet Diversification
A1: Diversification comparison
A3: Measure | B3: Amount (EUR)
A4: Approved diversification benefit | B4: 35000000
A5: Amount embedded in workbook formula | B5: 47000000

Sheet Capital Summary
A1: Solvency capital summary
A2: The two columns must remain distinct: approved basis versus workbook calculation.
A4: Metric | B4: Approved basis | C4: Workbook calculation
A5: Eligible own funds | B5: ='Own Funds'!B7 -> 180000000 | C5: ='Own Funds'!B7 -> 180000000
A6: SCR before diversification | B6: ='SCR Modules'!D9 -> 150000000 | C6: ='SCR Modules'!D9 -> 150000000
A7: Diversification benefit | B7: =-Assumptions!$B$4 -> -35000000 | C7: =-Diversification!$B$5 -> -47000000
A8: Operational risk | B8: =Assumptions!$B$5 -> 8000000 | C8: =Assumptions!$B$5 -> 8000000
A9: Final SCR | B9: =ROUND(B6-Assumptions!$B$4+B8,0) -> 123000000 | C9: =ROUND(C6-47000000+C8,0) -> 111000000
A10: Solvency ratio | B10: =ROUND(B5/B9,3) -> 1.463 | C10: =ROUND(C5/C9,3) -> 1.622
A11: Internal capital-management floor | B11: =Assumptions!$B$6 -> 1.5 | C11: =Assumptions!$B$6 -> 1.5
A12: Management indicator | B12: =IF(B10>=B11,"Dividend review may be considered","Below management floor") -> Below management floor | C12: =IF(C10>=C11,"Dividend review may be considered","Below management floor") -> Dividend review may be considered

Sheet QRT Bridge
A1: Approved-capital reconciliation bridge
A2: Only the monetary Final SCR is designated. The solvency ratio is a management metric.
A3: Authoritative output | B3: Workbook amount (EUR) | C3: Reference basis
A4: Final SCR | B4: ='Capital Summary'!C9 -> 111000000 | C4: Approved capital result: EUR 123.0 million
