Workbook

Sheet Assumptions
A1: Synthetic IFRS 17-related assumptions
A2: Editable inputs | B2: Value | C2: Unit / use | H2: Currency | I2: EUR rate | K2: Product | L2: Loss ratio
A3: Discount rate | B3: 0.035 | C3: Interest accretion
A4: Service movement rate | B4: 0.08 | C4: Claims and service movement | H4: EUR | I4: 1 | K4: Term Life | L4: 0.62
A5: Expense loading | B5: 0.02 | C5: Expense movement | H5: GBP | I5: 1.15 | K5: Annuity | L5: 0.7
A6: Assumption strengthening rate | B6: 0.015 | C6: Reserve strengthening | K6: Savings | L6: 0.55
A7: Reporting FX baseline | B7: 1 | C7: FX movement baseline
A8: Rounding significance | B8: 100 | C8: CEILING/FLOOR controls
A9: Upper display precision | B9: 0 | C9: ROUNDUP control
A10: Lower display precision | B10: 0 | C10: ROUNDDOWN control
A11: Zero value | B11: 0 | C11: Explicit zero branch
A12: Exposure unit divisor | B12: 100000 | C12: Whole exposure units

Sheet CohortData
A1: Synthetic policy cohort data and calculated attributes
A2: Aurora Mutual Life SE (synthetic); 2025-Q4; reporting currency EUR
A3: Cohort ID | B3: Entity | C3: Product | D3: Currency | E3: Premium | F3: Expected claims input | G3: Opening reserve input | H3: Included | I3: FX to EUR | J3: Product index | K3: Loss ratio | L3: Modelled claims | M3: Absolute input variance | N3: Exposure units
A4: SYN-0001 | B4: Aurora Mutual Life SE (synthetic) | C4: Term Life | D4: EUR | E4: 427000 | F4: 264740 | G4: 158844 | H4: =TRUE() -> 1 | I4: =VLOOKUP(D4,Assumptions!$H$4:$I$5,2,FALSE()) -> 1 | J4: =MATCH(C4,Assumptions!$K$4:$K$6,0) -> 1 | K4: =INDEX(Assumptions!$L$4:$L$6,J4) -> 0.62 | L4: =IF(H4,ROUND(E4*K4,2),Assumptions!$B$11) -> 264740 | M4: =ABS(F4-L4) -> 0 | N4: =INT(E4/Assumptions!$B$12) -> 4
A5: SYN-0002 | B5: Aurora Mutual Life SE (synthetic) | C5: Annuity | D5: EUR | E5: 157000 | F5: 109900 | G5: 65940 | H5: =TRUE() -> 1 | I5: =VLOOKUP(D5,Assumptions!$H$4:$I$5,2,FALSE()) -> 1 | J5: =MATCH(C5,Assumptions!$K$4:$K$6,0) -> 2 | K5: =INDEX(Assumptions!$L$4:$L$6,J5) -> 0.7 | L5: =IF(H5,ROUND(E5*K5,2),Assumptions!$B$11) -> 109900 | M5: =ABS(F5-L5) -> 0 | N5: =INT(E5/Assumptions!$B$12) -> 1
A6: SYN-0003 | B6: Aurora Mutual Life SE (synthetic) | C6: Savings | D6: EUR | E6: 112000 | F6: 61600 | G6: 36960 | H6: =TRUE() -> 1 | I6: =VLOOKUP(D6,Assumptions!$H$4:$I$5,2,FALSE()) -> 1 | J6: =MATCH(C6,Assumptions!$K$4:$K$6,0) -> 3 | K6: =INDEX(Assumptions!$L$4:$L$6,J6) -> 0.55 | L6: =IF(H6,ROUND(E6*K6,2),Assumptions!$B$11) -> 61600 | M6: =ABS(F6-L6) -> 0 | N6: =INT(E6/Assumptions!$B$12) -> 1
A7: SYN-0004 | B7: Aurora Mutual Life SE (synthetic) | C7: Term Life | D7: GBP | E7: 479000 | F7: 296980 | G7: 178188 | H7: =TRUE() -> 1 | I7: =VLOOKUP(D7,Assumptions!$H$4:$I$5,2,FALSE()) -> 1.15 | J7: =MATCH(C7,Assumptions!$K$4:$K$6,0) -> 1 | K7: =INDEX(Assumptions!$L$4:$L$6,J7) -> 0.62 | L7: =IF(H7,ROUND(E7*K7,2),Assumptions!$B$11) -> 296980 | M7: =ABS(F7-L7) -> 0 | N7: =INT(E7/Assumptions!$B$12) -> 4
A8: SYN-0005 | B8: Aurora Mutual Life SE (synthetic) | C8: Annuity | D8: EUR | E8: 240000 | F8: 168000 | G8: 100800 | H8: =TRUE() -> 1 | I8: =VLOOKUP(D8,Assumptions!$H$4:$I$5,2,FALSE()) -> 1 | J8: =MATCH(C8,Assumptions!$K$4:$K$6,0) -> 2 | K8: =INDEX(Assumptions!$L$4:$L$6,J8) -> 0.7 | L8: =IF(H8,ROUND(E8*K8,2),Assumptions!$B$11) -> 168000 | M8: =ABS(F8-L8) -> 0 | N8: =INT(E8/Assumptions!$B$12) -> 2
A9: SYN-0006 | B9: Aurora Mutual Life SE (synthetic) | C9: Savings | D9: EUR | E9: 225000 | F9: 123750 | G9: 74250 | H9: =TRUE() -> 1 | I9: =VLOOKUP(D9,Assumptions!$H$4:$I$5,2,FALSE()) -> 1 | J9: =MATCH(C9,Assumptions!$K$4:$K$6,0) -> 3 | K9: =INDEX(Assumptions!$L$4:$L$6,J9) -> 0.55 | L9: =IF(H9,ROUND(E9*K9,2),Assumptions!$B$11) -> 123750 | M9: =ABS(F9-L9) -> 0 | N9: =INT(E9/Assumptions!$B$12) -> 2
A10: SYN-0007 | B10: Aurora Mutual Life SE (synthetic) | C10: Term Life | D10: EUR | E10: 214000 | F10: 132680 | G10: 79608 | H10: =TRUE() -> 1 | I10: =VLOOKUP(D10,Assumptions!$H$4:$I$5,2,FALSE()) -> 1 | J10: =MATCH(C10,Assumptions!$K$4:$K$6,0) -> 1 | K10: =INDEX(Assumptions!$L$4:$L$6,J10) -> 0.62 | L10: =IF(H10,ROUND(E10*K10,2),Assumptions!$B$11) -> 132680 | M10: =ABS(F10-L10) -> 0 | N10: =INT(E10/Assumptions!$B$12) -> 2
A11: SYN-0008 | B11: Aurora Mutual Life SE (synthetic) | C11: Annuity | D11: GBP | E11: 171000 | F11: 119700 | G11: 71820 | H11: =TRUE() -> 1 | I11: =VLOOKUP(D11,Assumptions!$H$4:$I$5,2,FALSE()) -> 1.15 | J11: =MATCH(C11,Assumptions!$K$4:$K$6,0) -> 2 | K11: =INDEX(Assumptions!$L$4:$L$6,J11) -> 0.7 | L11: =IF(H11,ROUND(E11*K11,2),Assumptions!$B$11) -> 119700 | M11: =ABS(F11-L11) -> 0 | N11: =INT(E11/Assumptions!$B$12) -> 1
A12: SYN-0009 | B12: Aurora Mutual Life SE (synthetic) | C12: Savings | D12: EUR | E12: 477000 | F12: 262350 | G12: 157410 | H12: =TRUE() -> 1 | I12: =VLOOKUP(D12,Assumptions!$H$4:$I$5,2,FALSE()) -> 1 | J12: =MATCH(C12,Assumptions!$K$4:$K$6,0) -> 3 | K12: =INDEX(Assumptions!$L$4:$L$6,J12) -> 0.55 | L12: =IF(H12,ROUND(E12*K12,2),Assumptions!$B$11) -> 262350 | M12: =ABS(F12-L12) -> 0 | N12: =INT(E12/Assumptions!$B$12) -> 4
A13: SYN-0010 | B13: Aurora Mutual Life SE (synthetic) | C13: Term Life | D13: EUR | E13: 152000 | F13: 94240 | G13: 56544 | H13: =TRUE() -> 1 | I13: =VLOOKUP(D13,Assumptions!$H$4:$I$5,2,FALSE()) -> 1 | J13: =MATCH(C13,Assumptions!$K$4:$K$6,0) -> 1 | K13: =INDEX(Assumptions!$L$4:$L$6,J13) -> 0.62 | L13: =IF(H13,ROUND(E13*K13,2),Assumptions!$B$11) -> 94240 | M13: =ABS(F13-L13) -> 0 | N13: =INT(E13/Assumptions!$B$12) -> 1
A14: SYN-0011 | B14: Aurora Mutual Life SE (synthetic) | C14: Annuity | D14: EUR | E14: 446000 | F14: 312200 | G14: 187320 | H14: =TRUE() -> 1 | I14: =VLOOKUP(D14,Assumptions!$H$4:$I$5,2,FALSE()) -> 1 | J14: =MATCH(C14,Assumptions!$K$4:$K$6,0) -> 2 | K14: =INDEX(Assumptions!$L$4:$L$6,J14) -> 0.7 | L14: =IF(H14,ROUND(E14*K14,2),Assumptions!$B$11) -> 312200 | M14: =ABS(F14-L14) -> 0 | N14: =INT(E14/Assumptions!$B$12) -> 4
A15: SYN-0012 | B15: Aurora Mutual Life SE (synthetic) | C15: Savings | D15: GBP | E15: 479000 | F15: 263450 | G15: 158070 | H15: =TRUE() -> 1 | I15: =VLOOKUP(D15,Assumptions!$H$4:$I$5,2,FALSE()) -> 1.15 | J15: =MATCH(C15,Assumptions!$K$4:$K$6,0) -> 3 | K15: =INDEX(Assumptions!$L$4:$L$6,J15) -> 0.55 | L15: =IF(H15,ROUND(E15*K15,2),Assumptions!$B$11) -> 263450 | M15: =ABS(F15-L15) -> 0 | N15: =INT(E15/Assumptions!$B$12) -> 4
... A19: SYN-0016 | B19: Aurora Mutual Life SE (synthetic) | C19: Term Life | D19: GBP | E19: 316000 | F19: 195920 | G19: 117552 | H19: =TRUE() -> 1 | I19: =VLOOKUP(D19,Assumptions!$H$4:$I$5,2,FALSE()) -> 1.15 | J19: =MATCH(C19,Assumptions!$K$4:$K$6,0) -> 1 | K19: =INDEX(Assumptions!$L$4:$L$6,J19) -> 0.62 | L19: =IF(H19,ROUND(E19*K19,2),Assumptions!$B$11) -> 195920 | M19: =ABS(F19-L19) -> 0 | N19: =INT(E19/Assumptions!$B$12) -> 3
A20: SYN-0017 | B20: Aurora Mutual Life SE (synthetic) | C20: Annuity | D20: EUR | E20: 116000 | F20: 81200 | G20: 48720 | H20: =FALSE() -> 0 | I20: =VLOOKUP(D20,Assumptions!$H$4:$I$5,2,FALSE()) -> 1 | J20: =MATCH(C20,Assumptions!$K$4:$K$6,0) -> 2 | K20: =INDEX(Assumptions!$L$4:$L$6,J20) -> 0.7 | L20: =IF(H20,ROUND(E20*K20,2),Assumptions!$B$11) -> 0 | M20: =ABS(F20-L20) -> 81200 | N20: =INT(E20/Assumptions!$B$12) -> 1
A21: SYN-0018 | B21: Aurora Mutual Life SE (synthetic) | C21: Savings | D21: EUR | E21: 115000 | F21: 63250 | G21: 37950 | H21: =TRUE() -> 1 | I21: =VLOOKUP(D21,Assumptions!$H$4:$I$5,2,FALSE()) -> 1 | J21: =MATCH(C21,Assumptions!$K$4:$K$6,0) -> 3 | K21: =INDEX(Assumptions!$L$4:$L$6,J21) -> 0.55 | L21: =IF(H21,ROUND(E21*K21,2),Assumptions!$B$11) -> 63250 | M21: =ABS(F21-L21) -> 0 | N21: =INT(E21/Assumptions!$B$12) -> 1
A22: SYN-0019 | B22: Aurora Mutual Life SE (synthetic) | C22: Term Life | D22: EUR | E22: 147000 | F22: 91140 | G22: 54684 | H22: =TRUE() -> 1 | I22: =VLOOKUP(D22,Assumptions!$H$4:$I$5,2,FALSE()) -> 1 | J22: =MATCH(C22,Assumptions!$K$4:$K$6,0) -> 1 | K22: =INDEX(Assumptions!$L$4:$L$6,J22) -> 0.62 | L22: =IF(H22,ROUND(E22*K22,2),Assumptions!$B$11) -> 91140 | M22: =ABS(F22-L22) -> 0 | N22: =INT(E22/Assumptions!$B$12) -> 1
A23: SYN-0020 | B23: Aurora Mutual Life SE (synthetic) | C23: Annuity | D23: GBP | E23: 211000 | F23: 147700 | G23: 88620 | H23: =TRUE() -> 1 | I23: =VLOOKUP(D23,Assumptions!$H$4:$I$5,2,FALSE()) -> 1.15 | J23: =MATCH(C23,Assumptions!$K$4:$K$6,0) -> 2 | K23: =INDEX(Assumptions!$L$4:$L$6,J23) -> 0.7 | L23: =IF(H23,ROUND(E23*K23,2),Assumptions!$B$11) -> 147700 | M23: =ABS(F23-L23) -> 0 | N23: =INT(E23/Assumptions!$B$12) -> 2
A24: SYN-0021 | B24: Aurora Mutual Life SE (synthetic) | C24: Savings | D24: EUR | E24: 219000 | F24: 120450 | G24: 72270 | H24: =TRUE() -> 1 | I24: =VLOOKUP(D24,Assumptions!$H$4:$I$5,2,FALSE()) -> 1 | J24: =MATCH(C24,Assumptions!$K$4:$K$6,0) -> 3 | K24: =INDEX(Assumptions!$L$4:$L$6,J24) -> 0.55 | L24: =IF(H24,ROUND(E24*K24,2),Assumptions!$B$11) -> 120450 | M24: =ABS(F24-L24) -> 0 | N24: =INT(E24/Assumptions!$B$12) -> 2
A25: SYN-0022 | B25: Aurora Mutual Life SE (synthetic) | C25: Term Life | D25: EUR | E25: 358000 | F25: 221960 | G25: 133176 | H25: =TRUE() -> 1 | I25: =VLOOKUP(D25,Assumptions!$H$4:$I$5,2,FALSE()) -> 1 | J25: =MATCH(C25,Assumptions!$K$4:$K$6,0) -> 1 | K25: =INDEX(Assumptions!$L$4:$L$6,J25) -> 0.62 | L25: =IF(H25,ROUND(E25*K25,2),Assumptions!$B$11) -> 221960 | M25: =ABS(F25-L25) -> 0 | N25: =INT(E25/Assumptions!$B$12) -> 3
A26: SYN-0023 | B26: Aurora Mutual Life SE (synthetic) | C26: Annuity | D26: EUR | E26: 408000 | F26: 285600 | G26: 171360 | H26: =TRUE() -> 1 | I26: =VLOOKUP(D26,Assumptions!$H$4:$I$5,2,FALSE()) -> 1 | J26: =MATCH(C26,Assumptions!$K$4:$K$6,0) -> 2 | K26: =INDEX(Assumptions!$L$4:$L$6,J26) -> 0.7 | L26: =IF(H26,ROUND(E26*K26,2),Assumptions!$B$11) -> 285600 | M26: =ABS(F26-L26) -> 0 | N26: =INT(E26/Assumptions!$B$12) -> 4
A27: SYN-0024 | B27: Aurora Mutual Life SE (synthetic) | C27: Savings | D27: GBP | E27: 113000 | F27: 62150 | G27: 37290 | H27: =TRUE() -> 1 | I27: =VLOOKUP(D27,Assumptions!$H$4:$I$5,2,FALSE()) -> 1.15 | J27: =MATCH(C27,Assumptions!$K$4:$K$6,0) -> 3 | K27: =INDEX(Assumptions!$L$4:$L$6,J27) -> 0.55 | L27: =IF(H27,ROUND(E27*K27,2),Assumptions!$B$11) -> 62150 | M27: =ABS(F27-L27) -> 0 | N27: =INT(E27/Assumptions!$B$12) -> 1
A28: SYN-0025 | B28: Aurora Mutual Life SE (synthetic) | C28: Term Life | D28: EUR | E28: 387000 | F28: 239940 | G28: 143964 | H28: =TRUE() -> 1 | I28: =VLOOKUP(D28,Assumptions!$H$4:$I$5,2,FALSE()) -> 1 | J28: =MATCH(C28,Assumptions!$K$4:$K$6,0) -> 1 | K28: =INDEX(Assumptions!$L$4:$L$6,J28) -> 0.62 | L28: =IF(H28,ROUND(E28*K28,2),Assumptions!$B$11) -> 239940 | M28: =ABS(F28-L28) -> 0 | N28: =INT(E28/Assumptions!$B$12) -> 3
A29: SYN-0026 | B29: Aurora Mutual Life SE (synthetic) | C29: Annuity | D29: EUR | E29: 201000 | F29: 140700 | G29: 84420 | H29: =TRUE() -> 1 | I29: =VLOOKUP(D29,Assumptions!$H$4:$I$5,2,FALSE()) -> 1 | J29: =MATCH(C29,Assumptions!$K$4:$K$6,0) -> 2 | K29: =INDEX(Assumptions!$L$4:$L$6,J29) -> 0.7 | L29: =IF(H29,ROUND(E29*K29,2),Assumptions!$B$11) -> 140700 | M29: =ABS(F29-L29) -> 0 | N29: =INT(E29/Assumptions!$B$12) -> 2
A30: SYN-0027 | B30: Aurora Mutual Life SE (synthetic) | C30: Savings | D30: EUR | E30: 466000 | F30: 256300 | G30: 153780 | H30: =TRUE() -> 1 | I30: =VLOOKUP(D30,Assumptions!$H$4:$I$5,2,FALSE()) -> 1 | J30: =MATCH(C30,Assumptions!$K$4:$K$6,0) -> 3 | K30: =INDEX(Assumptions!$L$4:$L$6,J30) -> 0.55 | L30: =IF(H30,ROUND(E30*K30,2),Assumptions!$B$11) -> 256300 | M30: =ABS(F30-L30) -> 0 | N30: =INT(E30/Assumptions!$B$12) -> 4
A31: SYN-0028 | B31: Aurora Mutual Life SE (synthetic) | C31: Term Life | D31: GBP | E31: 432000 | F31: 267840 | G31: 160704 | H31: =TRUE() -> 1 | I31: =VLOOKUP(D31,Assumptions!$H$4:$I$5,2,FALSE()) -> 1.15 | J31: =MATCH(C31,Assumptions!$K$4:$K$6,0) -> 1 | K31: =INDEX(Assumptions!$L$4:$L$6,J31) -> 0.62 | L31: =IF(H31,ROUND(E31*K31,2),Assumptions!$B$11) -> 267840 | M31: =ABS(F31-L31) -> 0 | N31: =INT(E31/Assumptions!$B$12) -> 4
A32: SYN-0029 | B32: Aurora Mutual Life SE (synthetic) | C32: Annuity | D32: EUR | E32: 459000 | F32: 321300 | G32: 192780 | H32: =TRUE() -> 1 | I32: =VLOOKUP(D32,Assumptions!$H$4:$I$5,2,FALSE()) -> 1 | J32: =MATCH(C32,Assumptions!$K$4:$K$6,0) -> 2 | K32: =INDEX(Assumptions!$L$4:$L$6,J32) -> 0.7 | L32: =IF(H32,ROUND(E32*K32,2),Assumptions!$B$11) -> 321300 | M32: =ABS(F32-L32) -> 0 | N32: =INT(E32/Assumptions!$B$12) -> 4
... A36: SYN-0033 | B36: Aurora Mutual Life SE (synthetic) | C36: Savings | D36: EUR | E36: 329000 | F36: 180950 | G36: 108570 | H36: =TRUE() -> 1 | I36: =VLOOKUP(D36,Assumptions!$H$4:$I$5,2,FALSE()) -> 1 | J36: =MATCH(C36,Assumptions!$K$4:$K$6,0) -> 3 | K36: =INDEX(Assumptions!$L$4:$L$6,J36) -> 0.55 | L36: =IF(H36,ROUND(E36*K36,2),Assumptions!$B$11) -> 180950 | M36: =ABS(F36-L36) -> 0 | N36: =INT(E36/Assumptions!$B$12) -> 3
A37: SYN-0034 | B37: Aurora Mutual Life SE (synthetic) | C37: Term Life | D37: EUR | E37: 401000 | F37: 248620 | G37: 149172 | H37: =FALSE() -> 0 | I37: =VLOOKUP(D37,Assumptions!$H$4:$I$5,2,FALSE()) -> 1 | J37: =MATCH(C37,Assumptions!$K$4:$K$6,0) -> 1 | K37: =INDEX(Assumptions!$L$4:$L$6,J37) -> 0.62 | L37: =IF(H37,ROUND(E37*K37,2),Assumptions!$B$11) -> 0 | M37: =ABS(F37-L37) -> 248620 | N37: =INT(E37/Assumptions!$B$12) -> 4
A38: SYN-0035 | B38: Aurora Mutual Life SE (synthetic) | C38: Annuity | D38: EUR | E38: 242000 | F38: 169400 | G38: 101640 | H38: =TRUE() -> 1 | I38: =VLOOKUP(D38,Assumptions!$H$4:$I$5,2,FALSE()) -> 1 | J38: =MATCH(C38,Assumptions!$K$4:$K$6,0) -> 2 | K38: =INDEX(Assumptions!$L$4:$L$6,J38) -> 0.7 | L38: =IF(H38,ROUND(E38*K38,2),Assumptions!$B$11) -> 169400 | M38: =ABS(F38-L38) -> 0 | N38: =INT(E38/Assumptions!$B$12) -> 2
A39: SYN-0036 | B39: Aurora Mutual Life SE (synthetic) | C39: Savings | D39: GBP | E39: 103000 | F39: 56650 | G39: 33990 | H39: =TRUE() -> 1 | I39: =VLOOKUP(D39,Assumptions!$H$4:$I$5,2,FALSE()) -> 1.15 | J39: =MATCH(C39,Assumptions!$K$4:$K$6,0) -> 3 | K39: =INDEX(Assumptions!$L$4:$L$6,J39) -> 0.55 | L39: =IF(H39,ROUND(E39*K39,2),Assumptions!$B$11) -> 56650 | M39: =ABS(F39-L39) -> 0 | N39: =INT(E39/Assumptions!$B$12) -> 1
A40: SYN-0037 | B40: Aurora Mutual Life SE (synthetic) | C40: Term Life | D40: EUR | E40: 488000 | F40: 302560 | G40: 181536 | H40: =TRUE() -> 1 | I40: =VLOOKUP(D40,Assumptions!$H$4:$I$5,2,FALSE()) -> 1 | J40: =MATCH(C40,Assumptions!$K$4:$K$6,0) -> 1 | K40: =INDEX(Assumptions!$L$4:$L$6,J40) -> 0.62 | L40: =IF(H40,ROUND(E40*K40,2),Assumptions!$B$11) -> 302560 | M40: =ABS(F40-L40) -> 0 | N40: =INT(E40/Assumptions!$B$12) -> 4
A41: SYN-0038 | B41: Aurora Mutual Life SE (synthetic) | C41: Annuity | D41: EUR | E41: 181000 | F41: 126700 | G41: 76020 | H41: =TRUE() -> 1 | I41: =VLOOKUP(D41,Assumptions!$H$4:$I$5,2,FALSE()) -> 1 | J41: =MATCH(C41,Assumptions!$K$4:$K$6,0) -> 2 | K41: =INDEX(Assumptions!$L$4:$L$6,J41) -> 0.7 | L41: =IF(H41,ROUND(E41*K41,2),Assumptions!$B$11) -> 126700 | M41: =ABS(F41-L41) -> 0 | N41: =INT(E41/Assumptions!$B$12) -> 1
A42: SYN-0039 | B42: Aurora Mutual Life SE (synthetic) | C42: Savings | D42: EUR | E42: 457000 | F42: 251350 | G42: 150810 | H42: =TRUE() -> 1 | I42: =VLOOKUP(D42,Assumptions!$H$4:$I$5,2,FALSE()) -> 1 | J42: =MATCH(C42,Assumptions!$K$4:$K$6,0) -> 3 | K42: =INDEX(Assumptions!$L$4:$L$6,J42) -> 0.55 | L42: =IF(H42,ROUND(E42*K42,2),Assumptions!$B$11) -> 251350 | M42: =ABS(F42-L42) -> 0 | N42: =INT(E42/Assumptions!$B$12) -> 4
A43: SYN-0040 | B43: Aurora Mutual Life SE (synthetic) | C43: Term Life | D43: GBP | E43: 316000 | F43: 195920 | G43: 117552 | H43: =TRUE() -> 1 | I43: =VLOOKUP(D43,Assumptions!$H$4:$I$5,2,FALSE()) -> 1.15 | J43: =MATCH(C43,Assumptions!$K$4:$K$6,0) -> 1 | K43: =INDEX(Assumptions!$L$4:$L$6,J43) -> 0.62 | L43: =IF(H43,ROUND(E43*K43,2),Assumptions!$B$11) -> 195920 | M43: =ABS(F43-L43) -> 0 | N43: =INT(E43/Assumptions!$B$12) -> 3
A44: SYN-0041 | B44: Aurora Mutual Life SE (synthetic) | C44: Annuity | D44: EUR | E44: 274000 | F44: 191800 | G44: 115080 | H44: =TRUE() -> 1 | I44: =VLOOKUP(D44,Assumptions!$H$4:$I$5,2,FALSE()) -> 1 | J44: =MATCH(C44,Assumptions!$K$4:$K$6,0) -> 2 | K44: =INDEX(Assumptions!$L$4:$L$6,J44) -> 0.7 | L44: =IF(H44,ROUND(E44*K44,2),Assumptions!$B$11) -> 191800 | M44: =ABS(F44-L44) -> 0 | N44: =INT(E44/Assumptions!$B$12) -> 2
A45: SYN-0042 | B45: Aurora Mutual Life SE (synthetic) | C45: Savings | D45: EUR | E45: 242000 | F45: 133100 | G45: 79860 | H45: =TRUE() -> 1 | I45: =VLOOKUP(D45,Assumptions!$H$4:$I$5,2,FALSE()) -> 1 | J45: =MATCH(C45,Assumptions!$K$4:$K$6,0) -> 3 | K45: =INDEX(Assumptions!$L$4:$L$6,J45) -> 0.55 | L45: =IF(H45,ROUND(E45*K45,2),Assumptions!$B$11) -> 133100 | M45: =ABS(F45-L45) -> 0 | N45: =INT(E45/Assumptions!$B$12) -> 2
A46: SYN-0043 | B46: Aurora Mutual Life SE (synthetic) | C46: Term Life | D46: EUR | E46: 179000 | F46: 110980 | G46: 66588 | H46: =TRUE() -> 1 | I46: =VLOOKUP(D46,Assumptions!$H$4:$I$5,2,FALSE()) -> 1 | J46: =MATCH(C46,Assumptions!$K$4:$K$6,0) -> 1 | K46: =INDEX(Assumptions!$L$4:$L$6,J46) -> 0.62 | L46: =IF(H46,ROUND(E46*K46,2),Assumptions!$B$11) -> 110980 | M46: =ABS(F46-L46) -> 0 | N46: =INT(E46/Assumptions!$B$12) -> 1
A47: SYN-0044 | B47: Aurora Mutual Life SE (synthetic) | C47: Annuity | D47: GBP | E47: 210000 | F47: 147000 | G47: 88200 | H47: =TRUE() -> 1 | I47: =VLOOKUP(D47,Assumptions!$H$4:$I$5,2,FALSE()) -> 1.15 | J47: =MATCH(C47,Assumptions!$K$4:$K$6,0) -> 2 | K47: =INDEX(Assumptions!$L$4:$L$6,J47) -> 0.7 | L47: =IF(H47,ROUND(E47*K47,2),Assumptions!$B$11) -> 147000 | M47: =ABS(F47-L47) -> 0 | N47: =INT(E47/Assumptions!$B$12) -> 2
A48: SYN-0045 | B48: Aurora Mutual Life SE (synthetic) | C48: Savings | D48: EUR | E48: 490000 | F48: 269500 | G48: 161700 | H48: =TRUE() -> 1 | I48: =VLOOKUP(D48,Assumptions!$H$4:$I$5,2,FALSE()) -> 1 | J48: =MATCH(C48,Assumptions!$K$4:$K$6,0) -> 3 | K48: =INDEX(Assumptions!$L$4:$L$6,J48) -> 0.55 | L48: =IF(H48,ROUND(E48*K48,2),Assumptions!$B$11) -> 269500 | M48: =ABS(F48-L48) -> 0 | N48: =INT(E48/Assumptions!$B$12) -> 4
A49: SYN-0046 | B49: Aurora Mutual Life SE (synthetic) | C49: Term Life | D49: EUR | E49: 272000 | F49: 168640 | G49: 101184 | H49: =TRUE() -> 1 | I49: =VLOOKUP(D49,Assumptions!$H$4:$I$5,2,FALSE()) -> 1 | J49: =MATCH(C49,Assumptions!$K$4:$K$6,0) -> 1 | K49: =INDEX(Assumptions!$L$4:$L$6,J49) -> 0.62 | L49: =IF(H49,ROUND(E49*K49,2),Assumptions!$B$11) -> 168640 | M49: =ABS(F49-L49) -> 0 | N49: =INT(E49/Assumptions!$B$12) -> 2
... A53: SYN-0050 | B53: Aurora Mutual Life SE (synthetic) | C53: Annuity | D53: EUR | E53: 149000 | F53: 104300 | G53: 62580 | H53: =TRUE() -> 1 | I53: =VLOOKUP(D53,Assumptions!$H$4:$I$5,2,FALSE()) -> 1 | J53: =MATCH(C53,Assumptions!$K$4:$K$6,0) -> 2 | K53: =INDEX(Assumptions!$L$4:$L$6,J53) -> 0.7 | L53: =IF(H53,ROUND(E53*K53,2),Assumptions!$B$11) -> 104300 | M53: =ABS(F53-L53) -> 0 | N53: =INT(E53/Assumptions!$B$12) -> 1
A54: SYN-0051 | B54: Aurora Mutual Life SE (synthetic) | C54: Savings | D54: EUR | E54: 283000 | F54: 155650 | G54: 93390 | H54: =FALSE() -> 0 | I54: =VLOOKUP(D54,Assumptions!$H$4:$I$5,2,FALSE()) -> 1 | J54: =MATCH(C54,Assumptions!$K$4:$K$6,0) -> 3 | K54: =INDEX(Assumptions!$L$4:$L$6,J54) -> 0.55 | L54: =IF(H54,ROUND(E54*K54,2),Assumptions!$B$11) -> 0 | M54: =ABS(F54-L54) -> 155650 | N54: =INT(E54/Assumptions!$B$12) -> 2
A55: SYN-0052 | B55: Aurora Mutual Life SE (synthetic) | C55: Term Life | D55: GBP | E55: 276000 | F55: 171120 | G55: 102672 | H55: =TRUE() -> 1 | I55: =VLOOKUP(D55,Assumptions!$H$4:$I$5,2,FALSE()) -> 1.15 | J55: =MATCH(C55,Assumptions!$K$4:$K$6,0) -> 1 | K55: =INDEX(Assumptions!$L$4:$L$6,J55) -> 0.62 | L55: =IF(H55,ROUND(E55*K55,2),Assumptions!$B$11) -> 171120 | M55: =ABS(F55-L55) -> 0 | N55: =INT(E55/Assumptions!$B$12) -> 2
A56: SYN-0053 | B56: Aurora Mutual Life SE (synthetic) | C56: Annuity | D56: EUR | E56: 409000 | F56: 286300 | G56: 171780 | H56: =TRUE() -> 1 | I56: =VLOOKUP(D56,Assumptions!$H$4:$I$5,2,FALSE()) -> 1 | J56: =MATCH(C56,Assumptions!$K$4:$K$6,0) -> 2 | K56: =INDEX(Assumptions!$L$4:$L$6,J56) -> 0.7 | L56: =IF(H56,ROUND(E56*K56,2),Assumptions!$B$11) -> 286300 | M56: =ABS(F56-L56) -> 0 | N56: =INT(E56/Assumptions!$B$12) -> 4
A57: SYN-0054 | B57: Aurora Mutual Life SE (synthetic) | C57: Savings | D57: EUR | E57: 235000 | F57: 129250 | G57: 77550 | H57: =TRUE() -> 1 | I57: =VLOOKUP(D57,Assumptions!$H$4:$I$5,2,FALSE()) -> 1 | J57: =MATCH(C57,Assumptions!$K$4:$K$6,0) -> 3 | K57: =INDEX(Assumptions!$L$4:$L$6,J57) -> 0.55 | L57: =IF(H57,ROUND(E57*K57,2),Assumptions!$B$11) -> 129250 | M57: =ABS(F57-L57) -> 0 | N57: =INT(E57/Assumptions!$B$12) -> 2
A58: SYN-0055 | B58: Aurora Mutual Life SE (synthetic) | C58: Term Life | D58: EUR | E58: 122000 | F58: 75640 | G58: 45384 | H58: =TRUE() -> 1 | I58: =VLOOKUP(D58,Assumptions!$H$4:$I$5,2,FALSE()) -> 1 | J58: =MATCH(C58,Assumptions!$K$4:$K$6,0) -> 1 | K58: =INDEX(Assumptions!$L$4:$L$6,J58) -> 0.62 | L58: =IF(H58,ROUND(E58*K58,2),Assumptions!$B$11) -> 75640 | M58: =ABS(F58-L58) -> 0 | N58: =INT(E58/Assumptions!$B$12) -> 1
A59: SYN-0056 | B59: Aurora Mutual Life SE (synthetic) | C59: Annuity | D59: GBP | E59: 473000 | F59: 331100 | G59: 198660 | H59: =TRUE() -> 1 | I59: =VLOOKUP(D59,Assumptions!$H$4:$I$5,2,FALSE()) -> 1.15 | J59: =MATCH(C59,Assumptions!$K$4:$K$6,0) -> 2 | K59: =INDEX(Assumptions!$L$4:$L$6,J59) -> 0.7 | L59: =IF(H59,ROUND(E59*K59,2),Assumptions!$B$11) -> 331100 | M59: =ABS(F59-L59) -> 0 | N59: =INT(E59/Assumptions!$B$12) -> 4
A60: SYN-0057 | B60: Aurora Mutual Life SE (synthetic) | C60: Savings | D60: EUR | E60: 335000 | F60: 184250 | G60: 110550 | H60: =TRUE() -> 1 | I60: =VLOOKUP(D60,Assumptions!$H$4:$I$5,2,FALSE()) -> 1 | J60: =MATCH(C60,Assumptions!$K$4:$K$6,0) -> 3 | K60: =INDEX(Assumptions!$L$4:$L$6,J60) -> 0.55 | L60: =IF(H60,ROUND(E60*K60,2),Assumptions!$B$11) -> 184250 | M60: =ABS(F60-L60) -> 0 | N60: =INT(E60/Assumptions!$B$12) -> 3
A61: SYN-0058 | B61: Aurora Mutual Life SE (synthetic) | C61: Term Life | D61: EUR | E61: 374000 | F61: 231880 | G61: 139128 | H61: =TRUE() -> 1 | I61: =VLOOKUP(D61,Assumptions!$H$4:$I$5,2,FALSE()) -> 1 | J61: =MATCH(C61,Assumptions!$K$4:$K$6,0) -> 1 | K61: =INDEX(Assumptions!$L$4:$L$6,J61) -> 0.62 | L61: =IF(H61,ROUND(E61*K61,2),Assumptions!$B$11) -> 231880 | M61: =ABS(F61-L61) -> 0 | N61: =INT(E61/Assumptions!$B$12) -> 3
A62: SYN-0059 | B62: Aurora Mutual Life SE (synthetic) | C62: Annuity | D62: EUR | E62: 163000 | F62: 114100 | G62: 68460 | H62: =TRUE() -> 1 | I62: =VLOOKUP(D62,Assumptions!$H$4:$I$5,2,FALSE()) -> 1 | J62: =MATCH(C62,Assumptions!$K$4:$K$6,0) -> 2 | K62: =INDEX(Assumptions!$L$4:$L$6,J62) -> 0.7 | L62: =IF(H62,ROUND(E62*K62,2),Assumptions!$B$11) -> 114100 | M62: =ABS(F62-L62) -> 0 | N62: =INT(E62/Assumptions!$B$12) -> 1
A63: SYN-0060 | B63: Aurora Mutual Life SE (synthetic) | C63: Savings | D63: GBP | E63: 293000 | F63: 161150 | G63: 96690 | H63: =TRUE() -> 1 | I63: =VLOOKUP(D63,Assumptions!$H$4:$I$5,2,FALSE()) -> 1.15 | J63: =MATCH(C63,Assumptions!$K$4:$K$6,0) -> 3 | K63: =INDEX(Assumptions!$L$4:$L$6,J63) -> 0.55 | L63: =IF(H63,ROUND(E63*K63,2),Assumptions!$B$11) -> 161150 | M63: =ABS(F63-L63) -> 0 | N63: =INT(E63/Assumptions!$B$12) -> 2
A64: SYN-0061 | B64: Aurora Mutual Life SE (synthetic) | C64: Term Life | D64: EUR | E64: 140000 | F64: 86800 | G64: 52080 | H64: =TRUE() -> 1 | I64: =VLOOKUP(D64,Assumptions!$H$4:$I$5,2,FALSE()) -> 1 | J64: =MATCH(C64,Assumptions!$K$4:$K$6,0) -> 1 | K64: =INDEX(Assumptions!$L$4:$L$6,J64) -> 0.62 | L64: =IF(H64,ROUND(E64*K64,2),Assumptions!$B$11) -> 86800 | M64: =ABS(F64-L64) -> 0 | N64: =INT(E64/Assumptions!$B$12) -> 1
A65: SYN-0062 | B65: Aurora Mutual Life SE (synthetic) | C65: Annuity | D65: EUR | E65: 382000 | F65: 267400 | G65: 160440 | H65: =TRUE() -> 1 | I65: =VLOOKUP(D65,Assumptions!$H$4:$I$5,2,FALSE()) -> 1 | J65: =MATCH(C65,Assumptions!$K$4:$K$6,0) -> 2 | K65: =INDEX(Assumptions!$L$4:$L$6,J65) -> 0.7 | L65: =IF(H65,ROUND(E65*K65,2),Assumptions!$B$11) -> 267400 | M65: =ABS(F65-L65) -> 0 | N65: =INT(E65/Assumptions!$B$12) -> 3
A66: SYN-0063 | B66: Aurora Mutual Life SE (synthetic) | C66: Savings | D66: EUR | E66: 250000 | F66: 137500 | G66: 82500 | H66: =TRUE() -> 1 | I66: =VLOOKUP(D66,Assumptions!$H$4:$I$5,2,FALSE()) -> 1 | J66: =MATCH(C66,Assumptions!$K$4:$K$6,0) -> 3 | K66: =INDEX(Assumptions!$L$4:$L$6,J66) -> 0.55 | L66: =IF(H66,ROUND(E66*K66,2),Assumptions!$B$11) -> 137500 | M66: =ABS(F66-L66) -> 0 | N66: =INT(E66/Assumptions!$B$12) -> 2
... A70: SYN-0067 | B70: Aurora Mutual Life SE (synthetic) | C70: Term Life | D70: EUR | E70: 395000 | F70: 244900 | G70: 146940 | H70: =TRUE() -> 1 | I70: =VLOOKUP(D70,Assumptions!$H$4:$I$5,2,FALSE()) -> 1 | J70: =MATCH(C70,Assumptions!$K$4:$K$6,0) -> 1 | K70: =INDEX(Assumptions!$L$4:$L$6,J70) -> 0.62 | L70: =IF(H70,ROUND(E70*K70,2),Assumptions!$B$11) -> 244900 | M70: =ABS(F70-L70) -> 0 | N70: =INT(E70/Assumptions!$B$12) -> 3
A71: SYN-0068 | B71: Aurora Mutual Life SE (synthetic) | C71: Annuity | D71: GBP | E71: 198000 | F71: 138600 | G71: 83160 | H71: =FALSE() -> 0 | I71: =VLOOKUP(D71,Assumptions!$H$4:$I$5,2,FALSE()) -> 1.15 | J71: =MATCH(C71,Assumptions!$K$4:$K$6,0) -> 2 | K71: =INDEX(Assumptions!$L$4:$L$6,J71) -> 0.7 | L71: =IF(H71,ROUND(E71*K71,2),Assumptions!$B$11) -> 0 | M71: =ABS(F71-L71) -> 138600 | N71: =INT(E71/Assumptions!$B$12) -> 1
A72: SYN-0069 | B72: Aurora Mutual Life SE (synthetic) | C72: Savings | D72: EUR | E72: 460000 | F72: 253000 | G72: 151800 | H72: =TRUE() -> 1 | I72: =VLOOKUP(D72,Assumptions!$H$4:$I$5,2,FALSE()) -> 1 | J72: =MATCH(C72,Assumptions!$K$4:$K$6,0) -> 3 | K72: =INDEX(Assumptions!$L$4:$L$6,J72) -> 0.55 | L72: =IF(H72,ROUND(E72*K72,2),Assumptions!$B$11) -> 253000 | M72: =ABS(F72-L72) -> 0 | N72: =INT(E72/Assumptions!$B$12) -> 4
A73: SYN-0070 | B73: Aurora Mutual Life SE (synthetic) | C73: Term Life | D73: EUR | E73: 135000 | F73: 83700 | G73: 50220 | H73: =TRUE() -> 1 | I73: =VLOOKUP(D73,Assumptions!$H$4:$I$5,2,FALSE()) -> 1 | J73: =MATCH(C73,Assumptions!$K$4:$K$6,0) -> 1 | K73: =INDEX(Assumptions!$L$4:$L$6,J73) -> 0.62 | L73: =IF(H73,ROUND(E73*K73,2),Assumptions!$B$11) -> 83700 | M73: =ABS(F73-L73) -> 0 | N73: =INT(E73/Assumptions!$B$12) -> 1
A74: SYN-0071 | B74: Aurora Mutual Life SE (synthetic) | C74: Annuity | D74: EUR | E74: 123000 | F74: 86100 | G74: 51660 | H74: =TRUE() -> 1 | I74: =VLOOKUP(D74,Assumptions!$H$4:$I$5,2,FALSE()) -> 1 | J74: =MATCH(C74,Assumptions!$K$4:$K$6,0) -> 2 | K74: =INDEX(Assumptions!$L$4:$L$6,J74) -> 0.7 | L74: =IF(H74,ROUND(E74*K74,2),Assumptions!$B$11) -> 86100 | M74: =ABS(F74-L74) -> 0 | N74: =INT(E74/Assumptions!$B$12) -> 1
A75: SYN-0072 | B75: Aurora Mutual Life SE (synthetic) | C75: Savings | D75: GBP | E75: 438000 | F75: 240900 | G75: 144540 | H75: =TRUE() -> 1 | I75: =VLOOKUP(D75,Assumptions!$H$4:$I$5,2,FALSE()) -> 1.15 | J75: =MATCH(C75,Assumptions!$K$4:$K$6,0) -> 3 | K75: =INDEX(Assumptions!$L$4:$L$6,J75) -> 0.55 | L75: =IF(H75,ROUND(E75*K75,2),Assumptions!$B$11) -> 240900 | M75: =ABS(F75-L75) -> 0 | N75: =INT(E75/Assumptions!$B$12) -> 4
A76: SYN-0073 | B76: Aurora Mutual Life SE (synthetic) | C76: Term Life | D76: EUR | E76: 216000 | F76: 133920 | G76: 80352 | H76: =TRUE() -> 1 | I76: =VLOOKUP(D76,Assumptions!$H$4:$I$5,2,FALSE()) -> 1 | J76: =MATCH(C76,Assumptions!$K$4:$K$6,0) -> 1 | K76: =INDEX(Assumptions!$L$4:$L$6,J76) -> 0.62 | L76: =IF(H76,ROUND(E76*K76,2),Assumptions!$B$11) -> 133920 | M76: =ABS(F76-L76) -> 0 | N76: =INT(E76/Assumptions!$B$12) -> 2
A77: SYN-0074 | B77: Aurora Mutual Life SE (synthetic) | C77: Annuity | D77: EUR | E77: 495000 | F77: 346500 | G77: 207900 | H77: =TRUE() -> 1 | I77: =VLOOKUP(D77,Assumptions!$H$4:$I$5,2,FALSE()) -> 1 | J77: =MATCH(C77,Assumptions!$K$4:$K$6,0) -> 2 | K77: =INDEX(Assumptions!$L$4:$L$6,J77) -> 0.7 | L77: =IF(H77,ROUND(E77*K77,2),Assumptions!$B$11) -> 346500 | M77: =ABS(F77-L77) -> 0 | N77: =INT(E77/Assumptions!$B$12) -> 4
A78: SYN-0075 | B78: Aurora Mutual Life SE (synthetic) | C78: Savings | D78: EUR | E78: 248000 | F78: 136400 | G78: 81840 | H78: =TRUE() -> 1 | I78: =VLOOKUP(D78,Assumptions!$H$4:$I$5,2,FALSE()) -> 1 | J78: =MATCH(C78,Assumptions!$K$4:$K$6,0) -> 3 | K78: =INDEX(Assumptions!$L$4:$L$6,J78) -> 0.55 | L78: =IF(H78,ROUND(E78*K78,2),Assumptions!$B$11) -> 136400 | M78: =ABS(F78-L78) -> 0 | N78: =INT(E78/Assumptions!$B$12) -> 2
A79: SYN-0076 | B79: Aurora Mutual Life SE (synthetic) | C79: Term Life | D79: GBP | E79: 140000 | F79: 86800 | G79: 52080 | H79: =TRUE() -> 1 | I79: =VLOOKUP(D79,Assumptions!$H$4:$I$5,2,FALSE()) -> 1.15 | J79: =MATCH(C79,Assumptions!$K$4:$K$6,0) -> 1 | K79: =INDEX(Assumptions!$L$4:$L$6,J79) -> 0.62 | L79: =IF(H79,ROUND(E79*K79,2),Assumptions!$B$11) -> 86800 | M79: =ABS(F79-L79) -> 0 | N79: =INT(E79/Assumptions!$B$12) -> 1
A80: SYN-0077 | B80: Aurora Mutual Life SE (synthetic) | C80: Annuity | D80: EUR | E80: 219000 | F80: 153300 | G80: 91980 | H80: =TRUE() -> 1 | I80: =VLOOKUP(D80,Assumptions!$H$4:$I$5,2,FALSE()) -> 1 | J80: =MATCH(C80,Assumptions!$K$4:$K$6,0) -> 2 | K80: =INDEX(Assumptions!$L$4:$L$6,J80) -> 0.7 | L80: =IF(H80,ROUND(E80*K80,2),Assumptions!$B$11) -> 153300 | M80: =ABS(F80-L80) -> 0 | N80: =INT(E80/Assumptions!$B$12) -> 2
A81: SYN-0078 | B81: Aurora Mutual Life SE (synthetic) | C81: Savings | D81: EUR | E81: 151000 | F81: 83050 | G81: 49830 | H81: =TRUE() -> 1 | I81: =VLOOKUP(D81,Assumptions!$H$4:$I$5,2,FALSE()) -> 1 | J81: =MATCH(C81,Assumptions!$K$4:$K$6,0) -> 3 | K81: =INDEX(Assumptions!$L$4:$L$6,J81) -> 0.55 | L81: =IF(H81,ROUND(E81*K81,2),Assumptions!$B$11) -> 83050 | M81: =ABS(F81-L81) -> 0 | N81: =INT(E81/Assumptions!$B$12) -> 1
A82: SYN-0079 | B82: Aurora Mutual Life SE (synthetic) | C82: Term Life | D82: EUR | E82: 294000 | F82: 182280 | G82: 109368 | H82: =TRUE() -> 1 | I82: =VLOOKUP(D82,Assumptions!$H$4:$I$5,2,FALSE()) -> 1 | J82: =MATCH(C82,Assumptions!$K$4:$K$6,0) -> 1 | K82: =INDEX(Assumptions!$L$4:$L$6,J82) -> 0.62 | L82: =IF(H82,ROUND(E82*K82,2),Assumptions!$B$11) -> 182280 | M82: =ABS(F82-L82) -> 0 | N82: =INT(E82/Assumptions!$B$12) -> 2
A83: SYN-0080 | B83: Aurora Mutual Life SE (synthetic) | C83: Annuity | D83: GBP | E83: 242000 | F83: 169400 | G83: 101640 | H83: =TRUE() -> 1 | I83: =VLOOKUP(D83,Assumptions!$H$4:$I$5,2,FALSE()) -> 1.15 | J83: =MATCH(C83,Assumptions!$K$4:$K$6,0) -> 2 | K83: =INDEX(Assumptions!$L$4:$L$6,J83) -> 0.7 | L83: =IF(H83,ROUND(E83*K83,2),Assumptions!$B$11) -> 169400 | M83: =ABS(F83-L83) -> 0 | N83: =INT(E83/Assumptions!$B$12) -> 2
... A87: SYN-0084 | B87: Aurora Mutual Life SE (synthetic) | C87: Savings | D87: GBP | E87: 183000 | F87: 100650 | G87: 60390 | H87: =TRUE() -> 1 | I87: =VLOOKUP(D87,Assumptions!$H$4:$I$5,2,FALSE()) -> 1.15 | J87: =MATCH(C87,Assumptions!$K$4:$K$6,0) -> 3 | K87: =INDEX(Assumptions!$L$4:$L$6,J87) -> 0.55 | L87: =IF(H87,ROUND(E87*K87,2),Assumptions!$B$11) -> 100650 | M87: =ABS(F87-L87) -> 0 | N87: =INT(E87/Assumptions!$B$12) -> 1
A88: SYN-0085 | B88: Aurora Mutual Life SE (synthetic) | C88: Term Life | D88: EUR | E88: 289000 | F88: 179180 | G88: 107508 | H88: =FALSE() -> 0 | I88: =VLOOKUP(D88,Assumptions!$H$4:$I$5,2,FALSE()) -> 1 | J88: =MATCH(C88,Assumptions!$K$4:$K$6,0) -> 1 | K88: =INDEX(Assumptions!$L$4:$L$6,J88) -> 0.62 | L88: =IF(H88,ROUND(E88*K88,2),Assumptions!$B$11) -> 0 | M88: =ABS(F88-L88) -> 179180 | N88: =INT(E88/Assumptions!$B$12) -> 2
A89: SYN-0086 | B89: Aurora Mutual Life SE (synthetic) | C89: Annuity | D89: EUR | E89: 281000 | F89: 196700 | G89: 118020 | H89: =TRUE() -> 1 | I89: =VLOOKUP(D89,Assumptions!$H$4:$I$5,2,FALSE()) -> 1 | J89: =MATCH(C89,Assumptions!$K$4:$K$6,0) -> 2 | K89: =INDEX(Assumptions!$L$4:$L$6,J89) -> 0.7 | L89: =IF(H89,ROUND(E89*K89,2),Assumptions!$B$11) -> 196700 | M89: =ABS(F89-L89) -> 0 | N89: =INT(E89/Assumptions!$B$12) -> 2
A90: SYN-0087 | B90: Aurora Mutual Life SE (synthetic) | C90: Savings | D90: EUR | E90: 207000 | F90: 113850 | G90: 68310 | H90: =TRUE() -> 1 | I90: =VLOOKUP(D90,Assumptions!$H$4:$I$5,2,FALSE()) -> 1 | J90: =MATCH(C90,Assumptions!$K$4:$K$6,0) -> 3 | K90: =INDEX(Assumptions!$L$4:$L$6,J90) -> 0.55 | L90: =IF(H90,ROUND(E90*K90,2),Assumptions!$B$11) -> 113850 | M90: =ABS(F90-L90) -> 0 | N90: =INT(E90/Assumptions!$B$12) -> 2
A91: SYN-0088 | B91: Aurora Mutual Life SE (synthetic) | C91: Term Life | D91: GBP | E91: 443000 | F91: 274660 | G91: 164796 | H91: =TRUE() -> 1 | I91: =VLOOKUP(D91,Assumptions!$H$4:$I$5,2,FALSE()) -> 1.15 | J91: =MATCH(C91,Assumptions!$K$4:$K$6,0) -> 1 | K91: =INDEX(Assumptions!$L$4:$L$6,J91) -> 0.62 | L91: =IF(H91,ROUND(E91*K91,2),Assumptions!$B$11) -> 274660 | M91: =ABS(F91-L91) -> 0 | N91: =INT(E91/Assumptions!$B$12) -> 4
A92: SYN-0089 | B92: Aurora Mutual Life SE (synthetic) | C92: Annuity | D92: EUR | E92: 236000 | F92: 165200 | G92: 99120 | H92: =TRUE() -> 1 | I92: =VLOOKUP(D92,Assumptions!$H$4:$I$5,2,FALSE()) -> 1 | J92: =MATCH(C92,Assumptions!$K$4:$K$6,0) -> 2 | K92: =INDEX(Assumptions!$L$4:$L$6,J92) -> 0.7 | L92: =IF(H92,ROUND(E92*K92,2),Assumptions!$B$11) -> 165200 | M92: =ABS(F92-L92) -> 0 | N92: =INT(E92/Assumptions!$B$12) -> 2
A93: SYN-0090 | B93: Aurora Mutual Life SE (synthetic) | C93: Savings | D93: EUR | E93: 459000 | F93: 252450 | G93: 151470 | H93: =TRUE() -> 1 | I93: =VLOOKUP(D93,Assumptions!$H$4:$I$5,2,FALSE()) -> 1 | J93: =MATCH(C93,Assumptions!$K$4:$K$6,0) -> 3 | K93: =INDEX(Assumptions!$L$4:$L$6,J93) -> 0.55 | L93: =IF(H93,ROUND(E93*K93,2),Assumptions!$B$11) -> 252450 | M93: =ABS(F93-L93) -> 0 | N93: =INT(E93/Assumptions!$B$12) -> 4
A94: SYN-0091 | B94: Aurora Mutual Life SE (synthetic) | C94: Term Life | D94: EUR | E94: 449000 | F94: 278380 | G94: 167028 | H94: =TRUE() -> 1 | I94: =VLOOKUP(D94,Assumptions!$H$4:$I$5,2,FALSE()) -> 1 | J94: =MATCH(C94,Assumptions!$K$4:$K$6,0) -> 1 | K94: =INDEX(Assumptions!$L$4:$L$6,J94) -> 0.62 | L94: =IF(H94,ROUND(E94*K94,2),Assumptions!$B$11) -> 278380 | M94: =ABS(F94-L94) -> 0 | N94: =INT(E94/Assumptions!$B$12) -> 4
A95: SYN-0092 | B95: Aurora Mutual Life SE (synthetic) | C95: Annuity | D95: GBP | E95: 431000 | F95: 301700 | G95: 181020 | H95: =TRUE() -> 1 | I95: =VLOOKUP(D95,Assumptions!$H$4:$I$5,2,FALSE()) -> 1.15 | J95: =MATCH(C95,Assumptions!$K$4:$K$6,0) -> 2 | K95: =INDEX(Assumptions!$L$4:$L$6,J95) -> 0.7 | L95: =IF(H95,ROUND(E95*K95,2),Assumptions!$B$11) -> 301700 | M95: =ABS(F95-L95) -> 0 | N95: =INT(E95/Assumptions!$B$12) -> 4
A96: SYN-0093 | B96: Aurora Mutual Life SE (synthetic) | C96: Savings | D96: EUR | E96: 136000 | F96: 74800 | G96: 44880 | H96: =TRUE() -> 1 | I96: =VLOOKUP(D96,Assumptions!$H$4:$I$5,2,FALSE()) -> 1 | J96: =MATCH(C96,Assumptions!$K$4:$K$6,0) -> 3 | K96: =INDEX(Assumptions!$L$4:$L$6,J96) -> 0.55 | L96: =IF(H96,ROUND(E96*K96,2),Assumptions!$B$11) -> 74800 | M96: =ABS(F96-L96) -> 0 | N96: =INT(E96/Assumptions!$B$12) -> 1
A97: SYN-0094 | B97: Aurora Mutual Life SE (synthetic) | C97: Term Life | D97: EUR | E97: 411000 | F97: 254820 | G97: 152892 | H97: =TRUE() -> 1 | I97: =VLOOKUP(D97,Assumptions!$H$4:$I$5,2,FALSE()) -> 1 | J97: =MATCH(C97,Assumptions!$K$4:$K$6,0) -> 1 | K97: =INDEX(Assumptions!$L$4:$L$6,J97) -> 0.62 | L97: =IF(H97,ROUND(E97*K97,2),Assumptions!$B$11) -> 254820 | M97: =ABS(F97-L97) -> 0 | N97: =INT(E97/Assumptions!$B$12) -> 4
A98: SYN-0095 | B98: Aurora Mutual Life SE (synthetic) | C98: Annuity | D98: EUR | E98: 425000 | F98: 297500 | G98: 178500 | H98: =TRUE() -> 1 | I98: =VLOOKUP(D98,Assumptions!$H$4:$I$5,2,FALSE()) -> 1 | J98: =MATCH(C98,Assumptions!$K$4:$K$6,0) -> 2 | K98: =INDEX(Assumptions!$L$4:$L$6,J98) -> 0.7 | L98: =IF(H98,ROUND(E98*K98,2),Assumptions!$B$11) -> 297500 | M98: =ABS(F98-L98) -> 0 | N98: =INT(E98/Assumptions!$B$12) -> 4
A99: SYN-0096 | B99: Aurora Mutual Life SE (synthetic) | C99: Savings | D99: GBP | E99: 187000 | F99: 102850 | G99: 61710 | H99: =TRUE() -> 1 | I99: =VLOOKUP(D99,Assumptions!$H$4:$I$5,2,FALSE()) -> 1.15 | J99: =MATCH(C99,Assumptions!$K$4:$K$6,0) -> 3 | K99: =INDEX(Assumptions!$L$4:$L$6,J99) -> 0.55 | L99: =IF(H99,ROUND(E99*K99,2),Assumptions!$B$11) -> 102850 | M99: =ABS(F99-L99) -> 0 | N99: =INT(E99/Assumptions!$B$12) -> 1
A100: SYN-0097 | B100: Aurora Mutual Life SE (synthetic) | C100: Term Life | D100: EUR | E100: 373000 | F100: 231260 | G100: 138756 | H100: =TRUE() -> 1 | I100: =VLOOKUP(D100,Assumptions!$H$4:$I$5,2,FALSE()) -> 1 | J100: =MATCH(C100,Assumptions!$K$4:$K$6,0) -> 1 | K100: =INDEX(Assumptions!$L$4:$L$6,J100) -> 0.62 | L100: =IF(H100,ROUND(E100*K100,2),Assumptions!$B$11) -> 231260 | M100: =ABS(F100-L100) -> 0 | N100: =INT(E100/Assumptions!$B$12) -> 3
... A104: SYN-0101 | B104: Aurora Mutual Life SE (synthetic) | C104: Annuity | D104: EUR | E104: 336000 | F104: 235200 | G104: 141120 | H104: =TRUE() -> 1 | I104: =VLOOKUP(D104,Assumptions!$H$4:$I$5,2,FALSE()) -> 1 | J104: =MATCH(C104,Assumptions!$K$4:$K$6,0) -> 2 | K104: =INDEX(Assumptions!$L$4:$L$6,J104) -> 0.7 | L104: =IF(H104,ROUND(E104*K104,2),Assumptions!$B$11) -> 235200 | M104: =ABS(F104-L104) -> 0 | N104: =INT(E104/Assumptions!$B$12) -> 3
A105: SYN-0102 | B105: Aurora Mutual Life SE (synthetic) | C105: Savings | D105: EUR | E105: 294000 | F105: 161700 | G105: 97020 | H105: =FALSE() -> 0 | I105: =VLOOKUP(D105,Assumptions!$H$4:$I$5,2,FALSE()) -> 1 | J105: =MATCH(C105,Assumptions!$K$4:$K$6,0) -> 3 | K105: =INDEX(Assumptions!$L$4:$L$6,J105) -> 0.55 | L105: =IF(H105,ROUND(E105*K105,2),Assumptions!$B$11) -> 0 | M105: =ABS(F105-L105) -> 161700 | N105: =INT(E105/Assumptions!$B$12) -> 2
A106: SYN-0103 | B106: Aurora Mutual Life SE (synthetic) | C106: Term Life | D106: EUR | E106: 238000 | F106: 147560 | G106: 88536 | H106: =TRUE() -> 1 | I106: =VLOOKUP(D106,Assumptions!$H$4:$I$5,2,FALSE()) -> 1 | J106: =MATCH(C106,Assumptions!$K$4:$K$6,0) -> 1 | K106: =INDEX(Assumptions!$L$4:$L$6,J106) -> 0.62 | L106: =IF(H106,ROUND(E106*K106,2),Assumptions!$B$11) -> 147560 | M106: =ABS(F106-L106) -> 0 | N106: =INT(E106/Assumptions!$B$12) -> 2
A107: SYN-0104 | B107: Aurora Mutual Life SE (synthetic) | C107: Annuity | D107: GBP | E107: 427000 | F107: 298900 | G107: 179340 | H107: =TRUE() -> 1 | I107: =VLOOKUP(D107,Assumptions!$H$4:$I$5,2,FALSE()) -> 1.15 | J107: =MATCH(C107,Assumptions!$K$4:$K$6,0) -> 2 | K107: =INDEX(Assumptions!$L$4:$L$6,J107) -> 0.7 | L107: =IF(H107,ROUND(E107*K107,2),Assumptions!$B$11) -> 298900 | M107: =ABS(F107-L107) -> 0 | N107: =INT(E107/Assumptions!$B$12) -> 4
A108: SYN-0105 | B108: Aurora Mutual Life SE (synthetic) | C108: Savings | D108: EUR | E108: 452000 | F108: 248600 | G108: 149160 | H108: =TRUE() -> 1 | I108: =VLOOKUP(D108,Assumptions!$H$4:$I$5,2,FALSE()) -> 1 | J108: =MATCH(C108,Assumptions!$K$4:$K$6,0) -> 3 | K108: =INDEX(Assumptions!$L$4:$L$6,J108) -> 0.55 | L108: =IF(H108,ROUND(E108*K108,2),Assumptions!$B$11) -> 248600 | M108: =ABS(F108-L108) -> 0 | N108: =INT(E108/Assumptions!$B$12) -> 4
A109: SYN-0106 | B109: Aurora Mutual Life SE (synthetic) | C109: Term Life | D109: EUR | E109: 385000 | F109: 238700 | G109: 143220 | H109: =TRUE() -> 1 | I109: =VLOOKUP(D109,Assumptions!$H$4:$I$5,2,FALSE()) -> 1 | J109: =MATCH(C109,Assumptions!$K$4:$K$6,0) -> 1 | K109: =INDEX(Assumptions!$L$4:$L$6,J109) -> 0.62 | L109: =IF(H109,ROUND(E109*K109,2),Assumptions!$B$11) -> 238700 | M109: =ABS(F109-L109) -> 0 | N109: =INT(E109/Assumptions!$B$12) -> 3
A110: SYN-0107 | B110: Aurora Mutual Life SE (synthetic) | C110: Annuity | D110: EUR | E110: 212000 | F110: 148400 | G110: 89040 | H110: =TRUE() -> 1 | I110: =VLOOKUP(D110,Assumptions!$H$4:$I$5,2,FALSE()) -> 1 | J110: =MATCH(C110,Assumptions!$K$4:$K$6,0) -> 2 | K110: =INDEX(Assumptions!$L$4:$L$6,J110) -> 0.7 | L110: =IF(H110,ROUND(E110*K110,2),Assumptions!$B$11) -> 148400 | M110: =ABS(F110-L110) -> 0 | N110: =INT(E110/Assumptions!$B$12) -> 2
A111: SYN-0108 | B111: Aurora Mutual Life SE (synthetic) | C111: Savings | D111: GBP | E111: 450000 | F111: 247500 | G111: 148500 | H111: =TRUE() -> 1 | I111: =VLOOKUP(D111,Assumptions!$H$4:$I$5,2,FALSE()) -> 1.15 | J111: =MATCH(C111,Assumptions!$K$4:$K$6,0) -> 3 | K111: =INDEX(Assumptions!$L$4:$L$6,J111) -> 0.55 | L111: =IF(H111,ROUND(E111*K111,2),Assumptions!$B$11) -> 247500 | M111: =ABS(F111-L111) -> 0 | N111: =INT(E111/Assumptions!$B$12) -> 4
A112: SYN-0109 | B112: Aurora Mutual Life SE (synthetic) | C112: Term Life | D112: EUR | E112: 266000 | F112: 164920 | G112: 98952 | H112: =TRUE() -> 1 | I112: =VLOOKUP(D112,Assumptions!$H$4:$I$5,2,FALSE()) -> 1 | J112: =MATCH(C112,Assumptions!$K$4:$K$6,0) -> 1 | K112: =INDEX(Assumptions!$L$4:$L$6,J112) -> 0.62 | L112: =IF(H112,ROUND(E112*K112,2),Assumptions!$B$11) -> 164920 | M112: =ABS(F112-L112) -> 0 | N112: =INT(E112/Assumptions!$B$12) -> 2
A113: SYN-0110 | B113: Aurora Mutual Life SE (synthetic) | C113: Annuity | D113: EUR | E113: 493000 | F113: 345100 | G113: 207060 | H113: =TRUE() -> 1 | I113: =VLOOKUP(D113,Assumptions!$H$4:$I$5,2,FALSE()) -> 1 | J113: =MATCH(C113,Assumptions!$K$4:$K$6,0) -> 2 | K113: =INDEX(Assumptions!$L$4:$L$6,J113) -> 0.7 | L113: =IF(H113,ROUND(E113*K113,2),Assumptions!$B$11) -> 345100 | M113: =ABS(F113-L113) -> 0 | N113: =INT(E113/Assumptions!$B$12) -> 4
A114: SYN-0111 | B114: Aurora Mutual Life SE (synthetic) | C114: Savings | D114: EUR | E114: 497000 | F114: 273350 | G114: 164010 | H114: =TRUE() -> 1 | I114: =VLOOKUP(D114,Assumptions!$H$4:$I$5,2,FALSE()) -> 1 | J114: =MATCH(C114,Assumptions!$K$4:$K$6,0) -> 3 | K114: =INDEX(Assumptions!$L$4:$L$6,J114) -> 0.55 | L114: =IF(H114,ROUND(E114*K114,2),Assumptions!$B$11) -> 273350 | M114: =ABS(F114-L114) -> 0 | N114: =INT(E114/Assumptions!$B$12) -> 4
A115: SYN-0112 | B115: Aurora Mutual Life SE (synthetic) | C115: Term Life | D115: GBP | E115: 128000 | F115: 79360 | G115: 47616 | H115: =TRUE() -> 1 | I115: =VLOOKUP(D115,Assumptions!$H$4:$I$5,2,FALSE()) -> 1.15 | J115: =MATCH(C115,Assumptions!$K$4:$K$6,0) -> 1 | K115: =INDEX(Assumptions!$L$4:$L$6,J115) -> 0.62 | L115: =IF(H115,ROUND(E115*K115,2),Assumptions!$B$11) -> 79360 | M115: =ABS(F115-L115) -> 0 | N115: =INT(E115/Assumptions!$B$12) -> 1
A116: SYN-0113 | B116: Aurora Mutual Life SE (synthetic) | C116: Annuity | D116: EUR | E116: 217000 | F116: 151900 | G116: 91140 | H116: =TRUE() -> 1 | I116: =VLOOKUP(D116,Assumptions!$H$4:$I$5,2,FALSE()) -> 1 | J116: =MATCH(C116,Assumptions!$K$4:$K$6,0) -> 2 | K116: =INDEX(Assumptions!$L$4:$L$6,J116) -> 0.7 | L116: =IF(H116,ROUND(E116*K116,2),Assumptions!$B$11) -> 151900 | M116: =ABS(F116-L116) -> 0 | N116: =INT(E116/Assumptions!$B$12) -> 2
A117: SYN-0114 | B117: Aurora Mutual Life SE (synthetic) | C117: Savings | D117: EUR | E117: 116000 | F117: 63800 | G117: 38280 | H117: =TRUE() -> 1 | I117: =VLOOKUP(D117,Assumptions!$H$4:$I$5,2,FALSE()) -> 1 | J117: =MATCH(C117,Assumptions!$K$4:$K$6,0) -> 3 | K117: =INDEX(Assumptions!$L$4:$L$6,J117) -> 0.55 | L117: =IF(H117,ROUND(E117*K117,2),Assumptions!$B$11) -> 63800 | M117: =ABS(F117-L117) -> 0 | N117: =INT(E117/Assumptions!$B$12) -> 1
... A121: SYN-0118 | B121: Aurora Mutual Life SE (synthetic) | C121: Term Life | D121: EUR | E121: 133000 | F121: 82460 | G121: 49476 | H121: =TRUE() -> 1 | I121: =VLOOKUP(D121,Assumptions!$H$4:$I$5,2,FALSE()) -> 1 | J121: =MATCH(C121,Assumptions!$K$4:$K$6,0) -> 1 | K121: =INDEX(Assumptions!$L$4:$L$6,J121) -> 0.62 | L121: =IF(H121,ROUND(E121*K121,2),Assumptions!$B$11) -> 82460 | M121: =ABS(F121-L121) -> 0 | N121: =INT(E121/Assumptions!$B$12) -> 1
...

Sheet ReserveRollforward
A1: Reserve roll-forward by synthetic cohort
A2: Amounts in EUR for 2025-Q4
A3: Cohort ID | B3: Opening reserve | C3: Claims / service movement | D3: Expense movement | E3: Interest accretion | F3: Assumption strengthening | G3: FX movement | H3: Closing reserve | I3: Ceiling control | J3: Floor control | K3: Rounded up | L3: Rounded down
A4: SYN-0001 | B4: =ROUND(CohortData!G4*CohortData!I4,2) -> 158844 | C4: =ROUND(CohortData!L4*Assumptions!$B$4*CohortData!I4,2) -> 21179.2 | D4: =ROUND(CohortData!E4*Assumptions!$B$5*CohortData!I4,2) -> 8540 | E4: =ROUND(B4*0.035,2) -> 5559.54 | F4: =ROUND(B4*Assumptions!$B$6,2) -> 2382.66 | G4: =ROUND(CohortData!G4*CohortData!I4-CohortData!G4*Assumptions!$B$7,2) -> 0 | H4: =SUM(B4:E4,F4:G4) -> 196505.4 | I4: =CEILING(H4,Assumptions!$B$8) -> 196600 | J4: =FLOOR(H4,Assumptions!$B$8) -> 196500 | K4: =ROUNDUP(H4,Assumptions!$B$9) -> 196506 | L4: =ROUNDDOWN(H4,Assumptions!$B$10) -> 196505
A5: SYN-0002 | B5: =ROUND(CohortData!G5*CohortData!I5,2) -> 65940 | C5: =ROUND(CohortData!L5*Assumptions!$B$4*CohortData!I5,2) -> 8792 | D5: =ROUND(CohortData!E5*Assumptions!$B$5*CohortData!I5,2) -> 3140 | E5: =ROUND(B5*Assumptions!$B$3,2) -> 2307.9 | F5: =ROUND(B5*Assumptions!$B$6,2) -> 989.1 | G5: =ROUND(CohortData!G5*CohortData!I5-CohortData!G5*Assumptions!$B$7,2) -> 0 | H5: =SUM(B5:E5,F5:G5) -> 81169 | I5: =CEILING(H5,Assumptions!$B$8) -> 81200 | J5: =FLOOR(H5,Assumptions!$B$8) -> 81100 | K5: =ROUNDUP(H5,Assumptions!$B$9) -> 81169 | L5: =ROUNDDOWN(H5,Assumptions!$B$10) -> 81169
A6: SYN-0003 | B6: =ROUND(CohortData!G6*CohortData!I6,2) -> 36960 | C6: =ROUND(CohortData!L6*Assumptions!$B$4*CohortData!I6,2) -> 4928 | D6: =ROUND(CohortData!E6*Assumptions!$B$5*CohortData!I6,2) -> 2240 | E6: =ROUND(B6*Assumptions!$B$3,2) -> 1293.6 | F6: =ROUND(B6*Assumptions!$B$6,2) -> 554.4 | G6: =ROUND(CohortData!G6*CohortData!I6-CohortData!G6*Assumptions!$B$7,2) -> 0 | H6: =SUM(B6:E6,F6:G6) -> 45976 | I6: =CEILING(H6,Assumptions!$B$8) -> 46000 | J6: =FLOOR(H6,Assumptions!$B$8) -> 45900 | K6: =ROUNDUP(H6,Assumptions!$B$9) -> 45976 | L6: =ROUNDDOWN(H6,Assumptions!$B$10) -> 45976
A7: SYN-0004 | B7: =ROUND(CohortData!G7*CohortData!I7,2) -> 204916.2 | C7: =ROUND(CohortData!L7*Assumptions!$B$4*CohortData!I7,2) -> 27322.16 | D7: =ROUND(CohortData!E7*Assumptions!$B$5*CohortData!I7,2) -> 11017 | E7: =ROUND(B7*Assumptions!$B$3,2) -> 7172.07 | F7: =ROUND(B7*Assumptions!$B$6,2) -> 3073.74 | G7: =ROUND(CohortData!G7*CohortData!I7-CohortData!G7*Assumptions!$B$7,2) -> 26728.2 | H7: =SUM(B7:E7,F7:G7) -> 280229.37 | I7: =CEILING(H7,Assumptions!$B$8) -> 280300 | J7: =FLOOR(H7,Assumptions!$B$8) -> 280200 | K7: =ROUNDUP(H7,Assumptions!$B$9) -> 280230 | L7: =ROUNDDOWN(H7,Assumptions!$B$10) -> 280229
A8: SYN-0005 | B8: =ROUND(CohortData!G8*CohortData!I8,2) -> 100800 | C8: =ROUND(CohortData!L8*Assumptions!$B$4*CohortData!I8,2) -> 13440 | D8: =ROUND(CohortData!E8*Assumptions!$B$5*CohortData!I8,2) -> 4800 | E8: =ROUND(B8*Assumptions!$B$3,2) -> 3528 | F8: =ROUND(B8*Assumptions!$B$6,2) -> 1512 | G8: =ROUND(CohortData!G8*CohortData!I8-CohortData!G8*Assumptions!$B$7,2) -> 0 | H8: =SUM(B8:E8,F8:G8) -> 124080 | I8: =CEILING(H8,Assumptions!$B$8) -> 124100 | J8: =FLOOR(H8,Assumptions!$B$8) -> 124000 | K8: =ROUNDUP(H8,Assumptions!$B$9) -> 124080 | L8: =ROUNDDOWN(H8,Assumptions!$B$10) -> 124080
A9: SYN-0006 | B9: =ROUND(CohortData!G9*CohortData!I9,2) -> 74250 | C9: =ROUND(CohortData!L9*Assumptions!$B$4*CohortData!I9,2) -> 9900 | D9: =ROUND(CohortData!E9*Assumptions!$B$5*CohortData!I9,2) -> 4500 | E9: =ROUND(B9*Assumptions!$B$3,2) -> 2598.75 | F9: =ROUND(B9*Assumptions!$B$6,2) -> 1113.75 | G9: =ROUND(CohortData!G9*CohortData!I9-CohortData!G9*Assumptions!$B$7,2) -> 0 | H9: =SUM(B9:E9,F9:G9) -> 92362.5 | I9: =CEILING(H9,Assumptions!$B$8) -> 92400 | J9: =FLOOR(H9,Assumptions!$B$8) -> 92300 | K9: =ROUNDUP(H9,Assumptions!$B$9) -> 92363 | L9: =ROUNDDOWN(H9,Assumptions!$B$10) -> 92362
A10: SYN-0007 | B10: =ROUND(CohortData!G10*CohortData!I10,2) -> 79608 | C10: =ROUND(CohortData!L10*Assumptions!$B$4*CohortData!I10,2) -> 10614.4 | D10: =ROUND(CohortData!E10*Assumptions!$B$5*CohortData!I10,2) -> 4280 | E10: =ROUND(B10*Assumptions!$B$3,2) -> 2786.28 | F10: =ROUND(B10*Assumptions!$B$6,2) -> 1194.12 | G10: =ROUND(CohortData!G10*CohortData!I10-CohortData!G10*Assumptions!$B$7,2) -> 0 | H10: =SUM(B10:E10,F10:G10) -> 98482.8 | I10: =CEILING(H10,Assumptions!$B$8) -> 98500 | J10: =FLOOR(H10,Assumptions!$B$8) -> 98400 | K10: =ROUNDUP(H10,Assumptions!$B$9) -> 98483 | L10: =ROUNDDOWN(H10,Assumptions!$B$10) -> 98482
A11: SYN-0008 | B11: =ROUND(CohortData!G11*CohortData!I11,2) -> 82593 | C11: =ROUND(CohortData!L11*Assumptions!$B$4*CohortData!I11,2) -> 11012.4 | D11: =ROUND(CohortData!E11*Assumptions!$B$5*CohortData!I11,2) -> 3933 | E11: =ROUND(B11*Assumptions!$B$3,2) -> 2890.76 | F11: =ROUND(B11*Assumptions!$B$6,2) -> 1238.9 | G11: =ROUND(CohortData!G11*CohortData!I11-CohortData!G11*Assumptions!$B$7,2) -> 10773 | H11: =SUM(B11:E11,F11:G11) -> 112441.06 | I11: =CEILING(H11,Assumptions!$B$8) -> 112500 | J11: =FLOOR(H11,Assumptions!$B$8) -> 112400 | K11: =ROUNDUP(H11,Assumptions!$B$9) -> 112442 | L11: =ROUNDDOWN(H11,Assumptions!$B$10) -> 112441
A12: SYN-0009 | B12: =ROUND(CohortData!G12*CohortData!I12,2) -> 157410 | C12: =ROUND(CohortData!L12*Assumptions!$B$4*CohortData!I12,2) -> 20988 | D12: =ROUND(CohortData!E12*Assumptions!$B$5*CohortData!I12,2) -> 9540 | E12: =ROUND(B12*Assumptions!$B$3,2) -> 5509.35 | F12: =ROUND(B12*Assumptions!$B$6,2) -> 2361.15 | G12: =ROUND(CohortData!G12*CohortData!I12-CohortData!G12*Assumptions!$B$7,2) -> 0 | H12: =SUM(B12:E12,F12:G12) -> 195808.5 | I12: =CEILING(H12,Assumptions!$B$8) -> 195900 | J12: =FLOOR(H12,Assumptions!$B$8) -> 195800 | K12: =ROUNDUP(H12,Assumptions!$B$9) -> 195809 | L12: =ROUNDDOWN(H12,Assumptions!$B$10) -> 195808
A13: SYN-0010 | B13: =ROUND(CohortData!G13*CohortData!I13,2) -> 56544 | C13: =ROUND(CohortData!L13*Assumptions!$B$4*CohortData!I13,2) -> 7539.2 | D13: =ROUND(CohortData!E13*Assumptions!$B$5*CohortData!I13,2) -> 3040 | E13: =ROUND(B13*Assumptions!$B$3,2) -> 1979.04 | F13: =ROUND(B13*Assumptions!$B$6,2) -> 848.16 | G13: =ROUND(CohortData!G13*CohortData!I13-CohortData!G13*Assumptions!$B$7,2) -> 0 | H13: =SUM(B13:E13,F13:G13) -> 69950.4 | I13: =CEILING(H13,Assumptions!$B$8) -> 70000 | J13: =FLOOR(H13,Assumptions!$B$8) -> 69900 | K13: =ROUNDUP(H13,Assumptions!$B$9) -> 69951 | L13: =ROUNDDOWN(H13,Assumptions!$B$10) -> 69950
A14: SYN-0011 | B14: =ROUND(CohortData!G14*CohortData!I14,2) -> 187320 | C14: =ROUND(CohortData!L14*Assumptions!$B$4*CohortData!I14,2) -> 24976 | D14: =ROUND(CohortData!E14*Assumptions!$B$5*CohortData!I14,2) -> 8920 | E14: =ROUND(B14*Assumptions!$B$3,2) -> 6556.2 | F14: =ROUND(B14*Assumptions!$B$6,2) -> 2809.8 | G14: =ROUND(CohortData!G14*CohortData!I14-CohortData!G14*Assumptions!$B$7,2) -> 0 | H14: =SUM(B14:E14,F14:G14) -> 230582 | I14: =CEILING(H14,Assumptions!$B$8) -> 230600 | J14: =FLOOR(H14,Assumptions!$B$8) -> 230500 | K14: =ROUNDUP(H14,Assumptions!$B$9) -> 230582 | L14: =ROUNDDOWN(H14,Assumptions!$B$10) -> 230582
A15: SYN-0012 | B15: =ROUND(CohortData!G15*CohortData!I15,2) -> 181780.5 | C15: =ROUND(CohortData!L15*Assumptions!$B$4*CohortData!I15,2) -> 24237.4 | D15: =ROUND(CohortData!E15*Assumptions!$B$5*CohortData!I15,2) -> 11017 | E15: =ROUND(B15*Assumptions!$B$3,2) -> 6362.32 | F15: =ROUND(B15*Assumptions!$B$6,2) -> 2726.71 | G15: =ROUND(CohortData!G15*CohortData!I15-CohortData!G15*Assumptions!$B$7,2) -> 23710.5 | H15: =SUM(B15:E15,F15:G15) -> 249834.43 | I15: =CEILING(H15,Assumptions!$B$8) -> 249900 | J15: =FLOOR(H15,Assumptions!$B$8) -> 249800 | K15: =ROUNDUP(H15,Assumptions!$B$9) -> 249835 | L15: =ROUNDDOWN(H15,Assumptions!$B$10) -> 249834
A16: SYN-0013 | B16: =ROUND(CohortData!G16*CohortData!I16,2) -> 140988 | C16: =ROUND(CohortData!L16*Assumptions!$B$4*CohortData!I16,2) -> 18798.4 | D16: =ROUND(CohortData!E16*Assumptions!$B$5*CohortData!I16,2) -> 7580 | E16: =ROUND(B16*Assumptions!$B$3,2) -> 4934.58 | F16: =ROUND(B16*Assumptions!$B$6,2) -> 2114.82 | G16: =ROUND(CohortData!G16*CohortData!I16-CohortData!G16*Assumptions!$B$7,2) -> 0 | H16: =SUM(B16:E16,F16:G16) -> 174415.8 | I16: =CEILING(H16,Assumptions!$B$8) -> 174500 | J16: =FLOOR(H16,Assumptions!$B$8) -> 174400 | K16: =ROUNDUP(H16,Assumptions!$B$9) -> 174416 | L16: =ROUNDDOWN(H16,Assumptions!$B$10) -> 174415
... A603: SYN-0600 | B603: =ROUND(CohortData!G603*CohortData!I603,2) -> 62617.5 | C603: =ROUND(CohortData!L603*Assumptions!$B$4*CohortData!I603,2) -> 8349 | D603: =ROUND(CohortData!E603*Assumptions!$B$5*CohortData!I603,2) -> 3795 | E603: =ROUND(B603*Assumptions!$B$3,2) -> 2191.61 | F603: =ROUND(B603*Assumptions!$B$6,2) -> 939.26 | G603: =ROUND(CohortData!G603*CohortData!I603-CohortData!G603*Assumptions!$B$7,2) -> 8167.5 | H603: =SUM(B603:E603,F603:G603) -> 86059.87 | I603: =CEILING(H603,Assumptions!$B$8) -> 86100 | J603: =FLOOR(H603,Assumptions!$B$8) -> 86000 | K603: =ROUNDUP(H603,Assumptions!$B$9) -> 86060 | L603: =ROUNDDOWN(H603,Assumptions!$B$10) -> 86059

Sheet Aggregation
A1: Product aggregation and distribution checks
A2: Synthetic portfolio summary for 2025-Q4
A3: Product | B3: Cohort count | C3: Included count | D3: Opening reserve | E3: Service movement | F3: Average closing | G3: Average included closing | H3: Minimum closing | I3: Maximum closing | J3: Closing reserve
A4: Term Life | B4: =COUNTIF(CohortData!$C$4:$C$603,A4) -> 200 | C4: =COUNTIFS(CohortData!$C$4:$C$603,A4,CohortData!$H$4:$H$603,TRUE()) -> 188 | D4: =SUMIF(CohortData!$C$4:$C$603,A4,ReserveRollforward!$B$4:$B$603) -> 22664156 | E4: =SUMIFS(ReserveRollforward!$C$4:$C$603,CohortData!$C$4:$C$603,A4,CohortData!$H$4:$H$603,TRUE()) -> 2828073 | F4: =AVERAGEIF(CohortData!$C$4:$C$603,A4,ReserveRollforward!$H$4:$H$603) -> 143220.84 | G4: =AVERAGEIFS(ReserveRollforward!$H$4:$H$603,CohortData!$C$4:$C$603,A4,CohortData!$H$4:$H$603,TRUE()) -> 143532.42 | H4: =_xlfn.MINIFS(ReserveRollforward!$H$4:$H$603,CohortData!$C$4:$C$603,A4) -> 46020 | I4: =_xlfn.MAXIFS(ReserveRollforward!$H$4:$H$603,CohortData!$C$4:$C$603,A4) -> 286079.67 | J4: =SUMIF(CohortData!$C$4:$C$603,A4,ReserveRollforward!$H$4:$H$603) -> 28644167
A5: Annuity | B5: =COUNTIF(CohortData!$C$4:$C$603,A5) -> 200 | C5: =COUNTIFS(CohortData!$C$4:$C$603,A5,CohortData!$H$4:$H$603,TRUE()) -> 188 | D5: =SUMIF(CohortData!$C$4:$C$603,A5,ReserveRollforward!$B$4:$B$603) -> 25773993 | E5: =SUMIFS(ReserveRollforward!$C$4:$C$603,CohortData!$C$4:$C$603,A5,CohortData!$H$4:$H$603,TRUE()) -> 3246485.2 | F5: =AVERAGEIF(CohortData!$C$4:$C$603,A5,ReserveRollforward!$H$4:$H$603) -> 162348.02 | G5: =AVERAGEIFS(ReserveRollforward!$H$4:$H$603,CohortData!$C$4:$C$603,A5,CohortData!$H$4:$H$603,TRUE()) -> 164128.16 | H5: =_xlfn.MINIFS(ReserveRollforward!$H$4:$H$603,CohortData!$C$4:$C$603,A5) -> 51700 | I5: =_xlfn.MAXIFS(ReserveRollforward!$H$4:$H$603,CohortData!$C$4:$C$603,A5) -> 328775 | J5: =SUMIF(CohortData!$C$4:$C$603,A5,ReserveRollforward!$H$4:$H$603) -> 32469604
A6: Savings | B6: =COUNTIF(CohortData!$C$4:$C$603,A6) -> 200 | C6: =COUNTIFS(CohortData!$C$4:$C$603,A6,CohortData!$H$4:$H$603,TRUE()) -> 189 | D6: =SUMIF(CohortData!$C$4:$C$603,A6,ReserveRollforward!$B$4:$B$603) -> 20260466 | E6: =SUMIFS(ReserveRollforward!$C$4:$C$603,CohortData!$C$4:$C$603,A6,CohortData!$H$4:$H$603,TRUE()) -> 2541275 | F6: =AVERAGEIF(CohortData!$C$4:$C$603,A6,ReserveRollforward!$H$4:$H$603) -> 128715.23 | G6: =AVERAGEIFS(ReserveRollforward!$H$4:$H$603,CohortData!$C$4:$C$603,A6,CohortData!$H$4:$H$603,TRUE()) -> 128941.87 | H6: =_xlfn.MINIFS(ReserveRollforward!$H$4:$H$603,CohortData!$C$4:$C$603,A6) -> 42692 | I6: =_xlfn.MAXIFS(ReserveRollforward!$H$4:$H$603,CohortData!$C$4:$C$603,A6) -> 252963.87 | J6: =SUMIF(CohortData!$C$4:$C$603,A6,ReserveRollforward!$H$4:$H$603) -> 25743046
A8: Portfolio total | B8: =SUM(B4:B6) -> 600 | C8: =SUM(C4:C6) -> 565 | D8: =SUM(D4:D6) -> 68698614 | E8: =SUM(E4:E6) -> 8615833.2 | F8: =SUM(F4:F6) -> 434284.09 | G8: =SUM(G4:G6) -> 436602.45 | H8: =SUM(H4:H6) -> 140412 | I8: =SUM(I4:I6) -> 867818.54 | J8: =SUM(J4:J4,J6:J6) -> 86856818

Sheet AccountingBridge
A1: Accounting bridge outputs
A2: Signed balances: credits are negative; all figures are synthetic.
A3: Account | B3: Output label | C3: Signed balance (EUR)
A4: SYN-2100 | B4: Opening reserve | C4: =-SUM(ReserveRollforward!B4:B603) -> -68698614
A5: SYN-2110 | B5: Claims and service movements | C5: =-SUM(ReserveRollforward!C4:C603) -> -8615833.2
A6: SYN-2120 | B6: Assumption strengthening amount | C6: =-SUM(ReserveRollforward!F4:F603) -> -1030479.4
A7: SYN-2130 | B7: FX movement | C7: =-SUM(ReserveRollforward!G4:G603) -> -2433696.3
A8: SYN-2140 | B8: Closing reserve | C8: =-SUM(ReserveRollforward!H4:H603) -> -86856818
A9: SYN-2199 | B9: Signed accounting balance | C9: =SUM(C4:C8)+OFFSET(Controls!B4,0,0) -> -1.6763544e+08
A10: SYN-2150 | B10: Expense movement output | C10: =-SUM(ReserveRollforward!D4:D603) -> -3673743

Sheet Controls
A1: Independent workbook controls
A2: A zero value is expected for each calculation.
A3: Control | B3: Difference (EUR)
A4: Closing reserve to roll-forward | B4: =AccountingBridge!C8+SUM(ReserveRollforward!H4:H603) -> 0
A5: Opening reserve to roll-forward | B5: =AccountingBridge!C4+SUM(ReserveRollforward!B4:B603) -> 0
A6: Accounting bridge signed total | B6: =AccountingBridge!C9-SUM(AccountingBridge!C4:C8) -> 0
A7: Aggregation closing reserve | B7: =ROUND(Aggregation!J8-SUM(ReserveRollforward!H4:H603),2) -> 0
A8: Absolute closing difference | B8: =ABS(B4) -> 0

Sheet DemoGuide
A1: Demonstration guide
A2: Scope | B2: Spreadsheet reconstruction and financial reconciliation around a synthetic IFRS 17-related process.
A3: Boundary | B3: This workbook does not implement or validate the full IFRS 17 methodology and is not an audit opinion.
A4: Synthetic data | B4: All entities, cohorts, accounts and amounts are fictional.
A5: Gate 2 authoritative output | B5: AccountingBridge!C9
A7: Cell | B7: Hand-checkable output | C7: Expected signed value (EUR)
A8: AccountingBridge!C4 | B8: Opening reserve | C8: -68698614
A9: AccountingBridge!C5 | B9: Claims and service movements | C9: -8615833.2
A10: AccountingBridge!C6 | B10: Assumption strengthening amount | C10: -1030479.4
A11: AccountingBridge!C7 | B11: FX movement | C11: -2433696.3
A12: AccountingBridge!C8 | B12: Closing reserve | C12: -86856818
A13: AccountingBridge!C9 | B13: Signed accounting balance | C13: -1.6763544e+08
A15: Demonstration sequence
A16: 1 | B16: Confirm entity, period, currency, basis, workbook hash and accounting reference context at Gate 1.
A17: 2 | B17: Review every finding and designate AccountingBridge!C9 at Gate 2.
A18: 3 | B18: Approve the proposed accounting mapping and set both materiality thresholds at Gate 3.
A19: 4 | B19: Create the named approval record at Gate 4; only then generate the PDF.
